Workbook

Sheet Cover
A1: Ironbridge Industrial Group — Digital transformation model
A2: Armageddon 2026 case submission support. Team ID: [to be added]. USD million unless stated; baseline FY2025; mandate Jan-2026 to Jun-2027. Plan shown at the base-case realisation factor (Assumptions).
A4: Win condition — is Ironbridge "turned around" by Jun-27?
A5: Test | B5: Unit | C5: Target | D5: Plan | E5: Result | F5: Why this test
A6: 1 Liquidity: new money needed beyond rollover + identified sources | B6: USD m | C6: =Assumptions!$C$91 -> 0 | D6: =Projection!$D$56 -> -10.97552 | E6: =IF(D6<=C6,"MET","NOT MET") -> MET | F6: Mandate is funded without fresh money (momentum needs it)
A7: 2 Solvency: exit interest cover, downside case (50% realisation) | B7: x | C7: =Assumptions!$C$92 -> 1 | D7: =Sensitivity!$C$9 -> 1.1127902 | E7: =IF(D7>=C7,"MET","NOT MET") -> MET | F7: Earnings cover interest even if only half the benefits land
A8: 3 Auto: run-rate EBITDA vs its share of maintenance capex | B8: USD m | C8: =Assumptions!$C$93 -> 20.454545 | D8: =Segments!$C$10 -> 28.686716 | E8: =IF(D8>=C8,"MET","NOT MET") -> MET | F8: Auto funds its own upkeep → no longer a cash drain, so no case for a forced sale
A9: 4 Digital: net digital contribution (run-rate) | B9: USD m | C9: =Assumptions!$C$94 -> 0 | D9: =Projection!$C$67 -> 8.728494 | E9: =IF(D9>C9,"MET","NOT MET") -> MET | F9: Digital pays for itself
A11: Key outputs
B12: Unit | C12: Base (momentum) | D12: Plan | E12: Δ | F12: Note
A13: EBITDA 2025A | B13: USD m | C13: =Projection!$C$9 -> 25
A14: EBITDA — Jun-27 run-rate | B14: USD m | C14: =Projection!$J$9 -> 48 | D14: =Projection!$K$9 -> 68.728494 | E14: =D14-C14 -> 20.728494 | F14: Base includes the automatic roll-off of 23 of 2025 implementation costs (Ex.6)
A15: EBITDA margin — Jun-27 run-rate | B15: % | C15: =Projection!$J$11 -> 0.040336134 | D15: =Projection!$K$11 -> 0.057354699 | E15: =D15-C15 -> 0.017018564
A16: EBITDA — last twelve months to Jun-27 | B16: USD m | C16: =Projection!$C$36 -> 45 | D16: =Projection!$D$36 -> 49.116935 | E16: =D16-C16 -> 4.1169345 | F16: What lenders test
A17: Free cash flow — 18 months | B17: USD m | C17: =Projection!$F$23 -> -141.73396 | D17: =Projection!$I$23 -> -74.02448 | E17: =D17-C17 -> 67.709476 | F17: Before disposals and financing
A18: Net debt — Jun-27 | B18: USD m | C18: =Projection!$E$28 -> 896.73396 | D18: =Projection!$H$28 -> 829.02448 | E18: =D18-C18 -> -67.709476 | F18: 2025: 755
A19: Net debt / LTM EBITDA — Jun-27 | B19: x | C19: =Projection!$C$40 -> 19.927421 | D19: =Projection!$D$40 -> 16.878588 | E19: =D19-C19 -> -3.0488337 | F19: 2025: 30.2x
A20: Interest cover — LTM to Jun-27 | B20: x | C20: =Projection!$C$38 -> 0.89571534 | D20: =Projection!$D$38 -> 1.0079719 | E20: =D20-C20 -> 0.11225661 | F20: 2025: 0.6x
A21: Interest cover — Jun-27 run-rate | B21: x | C21: =Projection!$C$42 -> 0.80567896 | D21: =Projection!$D$42 -> 1.275155 | E21: =D21-C21 -> 0.46947607
A22: New money to raise (after rollover and identified sources) | B22: USD m | C22: =Projection!$C$56 -> 56.733956 | D22: =Projection!$D$56 -> -10.97552 | E22: =D22-C22 -> -67.709476 | F22: Sources & uses on Projection
A23: Run-rate EBITDA vs free-cash-flow break-even | B23: USD m | C23: =Projection!$C$45 -> -91.57708 | D23: =Projection!$D$45 -> -50.169654 | E23: =D23-C23 -> 41.407427 | F23: Negative: balance-sheet action needed beyond Jun-27
A24: Auto EBITDA margin — Jun-27 run-rate (plan) | B24: % | D24: =Segments!$C$13 -> 0.050139548 | F24: 2025: 0.9%
A25: Net digital contribution — 2025 vs Jun-27 run-rate (plan) | B25: USD m | C25: =Diagnosis!$C$61 -> -35 | D25: =Projection!$C$67 -> 8.728494 | E25: =D25-C25 -> 43.728494 | F25: Column C here = 2025 actual, not base
A26: Run-rate EBITDA at 100% realisation (stretch) / 50% (downside) | B26: USD m | C26: =Sensitivity!$E$6 -> 77.479659 | D26: =Sensitivity!$C$6 -> 59.977329 | F26: C = stretch, D = downside
A28: Integrity checks (all should read OK)
A29: Check | C29: Value | D29: Status
A30: Balance sheet balances (2022–25) | C30: =ABS(Case_Financials!$C$50)+ABS(Case_Financials!$D$50)+ABS(Case_Financials!$E$50)+ABS(Case_Financials!$F$50) -> 0 | D30: =IF(ABS(C30)<0.001,"OK","CHECK") -> OK
A31: Rebuilt EBITDA = case-reported (2022–25) | C31: =ABS(Case_Financials!$C$10-Case_Financials!$C$17)+ABS(Case_Financials!$D$10-Case_Financials!$D$17)+ABS(Case_Financials!$E$10-Case_Financials!$E$17)+ABS(Case_Financials!$F$10-Case_Financials!$F$17) -> 0 | D31: =IF(ABS(C31)<0.001,"OK","CHECK") -> OK
A32: Rebuilt net income = case-reported (2022–25) | C32: =ABS(Case_Financials!$C$16-Case_Financials!$C$18)+ABS(Case_Financials!$D$16-Case_Financials!$D$18)+ABS(Case_Financials!$E$16-Case_Financials!$E$18)+ABS(Case_Financials!$F$16-Case_Financials!$F$18) -> 0 | D32: =IF(ABS(C32)<0.001,"OK","CHECK") -> OK
A33: Opex breakdown = case total (2022–25) | C33: =ABS(Case_Financials!$C$9-Case_Financials!$C$26)+ABS(Case_Financials!$D$9-Case_Financials!$D$26)+ABS(Case_Financials!$E$9-Case_Financials!$E$26)+ABS(Case_Financials!$F$9-Case_Financials!$F$26) -> 0 | D33: =IF(ABS(C33)<0.001,"OK","CHECK") -> OK
A34: Segments reconcile to Group revenue & EBITDA | C34: =ABS(Case_Financials!$C$57-Case_Financials!$C$6)+ABS(Case_Financials!$C$61-Case_Financials!$C$10)+ABS(Case_Financials!$D$57-Case_Financials!$D$6)+ABS(Case_Financials!$D$61-Case_Financials!$D$10)+ABS(Case_Financials!$E$57-Case_Financials!$E$6)+ABS(Case_Financials!$E$61-Case_Financials!$E$10)+ABS(Case_Financials!$F$57-Case_Financials!$F$6)+ABS(Case_Financials!$F$61-Case_Financials!$F$10) -> 0 | D34: =IF(ABS(C34)<0.001,"OK","CHECK") -> OK
A35: Cash-flow closing cash = balance sheet (2023–25) | C35: =ABS(Case_Financials!$D$81)+ABS(Case_Financials!$E$81)+ABS(Case_Financials!$F$81) -> 0 | D35: =IF(ABS(C35)<0.001,"OK","CHECK") -> OK
A36: Debt raised = change in total debt (2023–25) | C36: =ABS(Case_Financials!$D$82)+ABS(Case_Financials!$E$82)+ABS(Case_Financials!$F$82) -> 0 | D36: =IF(ABS(C36)<0.001,"OK","CHECK") -> OK
A37: D&A split = total D&A (2023–25) | C37: =ABS(Case_Financials!$D$86)+ABS(Case_Financials!$E$86)+ABS(Case_Financials!$F$86) -> 0 | D37: =IF(ABS(C37)<0.001,"OK","CHECK") -> OK
A38: Working-capital change = cash-flow line (2023–25) | C38: =ABS(Diagnosis!$D$20)+ABS(Diagnosis!$E$20)+ABS(Diagnosis!$F$20) -> 0 | D38: =IF(ABS(C38)<0.001,"OK","CHECK") -> OK
A39: Ex.6 cost breakdown = Ex.5 operating cost | C39: =ABS(Case_Digital!$C$24)+ABS(Case_Digital!$D$24)+ABS(Case_Digital!$E$24) -> 0 | D39: =IF(ABS(C39)<0.001,"OK","CHECK") -> OK
A40: Project + central digital opex = Ex.1 digital opex | C40: =Diagnosis!$C$60 -> 0 | D40: =IF(ABS(C40)<0.001,"OK","CHECK") -> OK
A41: EBITDA bridge 2022→25 closes | C41: =Diagnosis!$C$42 -> 0 | D41: =IF(ABS(C41)<0.001,"OK","CHECK") -> OK
A42: Initiative segment splits sum to 100% | C42: =SUM(Initiatives!$X$27:$X$41)-ROWS(Initiatives!$X$27:$X$41) -> 0 | D42: =IF(ABS(C42)<0.001,"OK","CHECK") -> OK
A43: Workstream view = initiative total | C43: =Initiatives!$C$55 -> 0 | D43: =IF(ABS(C43)<0.001,"OK","CHECK") -> OK
A44: Segment run-rates sum to Group run-rate | C44: =Segments!$F$11 -> 0 | D44: =IF(ABS(C44)<0.001,"OK","CHECK") -> OK
A45: Sources = uses (plan) | C45: =Projection!$D$57-Projection!$D$51 -> 0 | D45: =IF(ABS(C45)<0.001,"OK","CHECK") -> OK
A46: Zero cash tax valid: highest projected PBT | C46: =MAX(Projection!$D$32:$K$32) -> -43.767091 | D46: =IF(C46<0,"OK","CHECK") -> OK | F46: Must be negative
A48: How to read this workbook
A49: Blue text | C49: Input typed from the case or an assumption
A50: Black text | C50: Formula
A51: Green text | C51: Direct link to another sheet
A52: Yellow fill | C52: Key driver or headline output
A54: Sheet guide
A55: Case_Financials | C55: Exhibits 1–4 typed in, subtotals rebuilt and reconciled
A56: Case_Digital | C56: Exhibits 5–7: programme economics, cost breakdown, KPIs
A57: Case_Ops | C57: Exhibit 8: footprint, energy, labour, digital readiness
A58: Diagnosis | C58: Ratios, EBITDA bridge, programme scorecard, Auto digital burden, consistency flag
A59: Assumptions | C59: Every judgement call with rationale, benchmark, funding bridge and win-condition targets
A60: Initiatives | C60: Run-rate economics, overlap netting, phasing, workstreams, segment split, working capital
A61: Projection | C61: Base vs plan EBITDA, cash, net debt, lender (LTM) view, sources & uses
A62: Segments | C62: Jun-27 run-rate by business, SMC break-even price, SMC exit case
A63: Sensitivity | C63: Realisation scenarios and one-at-a-time shocks
A64: Sources | C64: External benchmarks with URLs

Sheet Case_Financials
A1: Case data — financial exhibits (USD m; FY ends 31 Dec)
A2: Blue = typed from the case exhibits. Black = formulas that rebuild case subtotals; "case-reported" rows are kept to prove the rebuild matches.
A4: Exhibit 1 — Income statement
A5: USD m | C5: 2022 | D5: 2023 | E5: 2024 | F5: 2025 | G5: Source / note
A6: Revenue | C6: 1150 | D6: 1205 | E6: 1230 | F6: 1190 | G6: Ex.1
A7: Cost of sales (excl. D&A) | C7: 860 | D7: 910 | E7: 945 | F7: 930 | G7: Ex.1. Includes energy and direct production labour (Ex.8) and the 2025 digital gross benefits (Ex.5)
A8: Gross profit | C8: =C6-C7 -> 290 | D8: =D6-D7 -> 295 | E8: =E6-E7 -> 285 | F8: =F6-F7 -> 260
A9: Operating expenses excl. D&A | C9: =SUM(C22:C25) -> 168 | D9: =SUM(D22:D25) -> 187 | E9: =SUM(E22:E25) -> 215 | F9: =SUM(F22:F25) -> 235 | G9: Sum of the Ex.1 opex breakdown below
A10: EBITDA | C10: =C8-C9 -> 122 | D10: =D8-D9 -> 108 | E10: =E8-E9 -> 70 | F10: =F8-F9 -> 25
A11: Depreciation & amortisation | C11: 58 | D11: 66 | E11: 78 | F11: 90 | G11: Ex.1
A12: EBIT | C12: =C10-C11 -> 64 | D12: =D10-D11 -> 42 | E12: =E10-E11 -> -8 | F12: =F10-F11 -> -65
A13: Net finance costs | C13: 24 | D13: 27 | E13: 33 | F13: 40 | G13: Ex.1 — interest on debt, net
A14: Profit before tax | C14: =C12-C13 -> 40 | D14: =D12-D13 -> 15 | E14: =E12-E13 -> -41 | F14: =F12-F13 -> -105
A15: Tax | C15: 10 | D15: 4 | E15: 0 | F15: 0 | G15: Ex.1 (2023 rounded to 4 per case footnote)
A16: Net income | C16: =C14-C15 -> 30 | D16: =D14-D15 -> 11 | E16: =E14-E15 -> -41 | F16: =F14-F15 -> -105
A17: EBITDA — case-reported | C17: 122 | D17: 108 | E17: 70 | F17: 25 | G17: Ex.1, for reconciliation
A18: Net income — case-reported | C18: 30 | D18: 11 | E18: -41 | F18: -105 | G18: Ex.1, for reconciliation
A20: Exhibit 1 — Operating expense breakdown
A21: USD m | C21: 2022 | D21: 2023 | E21: 2024 | F21: 2025
A22: Non-digital personnel costs | C22: 90 | D22: 95 | E22: 101 | F22: 108 | G22: Ex.1
A23: Selling and customer support | C23: 35 | D23: 38 | E23: 42 | F23: 45 | G23: Ex.1
A24: Digital and AI operating costs | C24: 8 | D24: 18 | E24: 35 | F24: 48 | G24: Ex.1 — expensed digital personnel, software, cloud, support, implementation
A25: Other overheads | C25: 35 | D25: 36 | E25: 37 | F25: 34 | G25: Ex.1
A26: Total operating expenses — case-reported | C26: 168 | D26: 187 | E26: 215 | F26: 235 | G26: Ex.1, for reconciliation
A28: Exhibit 2 — Balance sheet
A29: USD m | C29: 2022 | D29: 2023 | E29: 2024 | F29: 2025
A30: Cash & cash equivalents | C30: 90 | D30: 75 | E30: 55 | F30: 30 | G30: Ex.2
A31: Trade receivables | C31: 150 | D31: 158 | E31: 168 | F31: 172 | G31: Ex.2
A32: Inventory | C32: 205 | D32: 220 | E32: 240 | F32: 255 | G32: Ex.2
A33: Other current assets | C33: 38 | D33: 40 | E33: 43 | F33: 45 | G33: Ex.2
A34: Total current assets | C34: =SUM(C30:C33) -> 483 | D34: =SUM(D30:D33) -> 493 | E34: =SUM(E30:E33) -> 506 | F34: =SUM(F30:F33) -> 502
A35: PPE (net) | C35: 590 | D35: 630 | E35: 660 | F35: 680 | G35: Ex.2
A36: Capitalised digital & AI assets | C36: 65 | D36: 100 | E36: 135 | F36: 155 | G36: Ex.2 — net carrying value; 65 opening balance = earlier systems
A37: Other intangible assets | C37: 192 | D37: 191 | E37: 159 | F37: 113 | G37: Ex.2
A38: Total non-current assets | C38: =SUM(C35:C37) -> 847 | D38: =SUM(D35:D37) -> 921 | E38: =SUM(E35:E37) -> 954 | F38: =SUM(F35:F37) -> 948
A39: TOTAL ASSETS | C39: =C34+C38 -> 1330 | D39: =D34+D38 -> 1414 | E39: =E34+E38 -> 1460 | F39: =F34+F38 -> 1450
A40: Trade payables | C40: 165 | D40: 178 | E40: 188 | F40: 195 | G40: Ex.2
A41: Short-term debt | C41: 90 | D41: 115 | E41: 145 | F41: 180 | G41: Ex.2
A42: Other current liabilities | C42: 55 | D42: 58 | E42: 60 | F42: 63 | G42: Ex.2
A43: Total current liabilities | C43: =SUM(C40:C42) -> 310 | D43: =SUM(D40:D42) -> 351 | E43: =SUM(E40:E42) -> 393 | F43: =SUM(F40:F42) -> 438
A44: Long-term debt | C44: 470 | D44: 510 | E44: 555 | F44: 605 | G44: Ex.2
A45: Other long-term liabilities | C45: 30 | D45: 30 | E45: 30 | F45: 30 | G45: Ex.2
A46: Total non-current liabilities | C46: =C44+C45 -> 500 | D46: =D44+D45 -> 540 | E46: =E44+E45 -> 585 | F46: =F44+F45 -> 635
A47: Total liabilities | C47: =C43+C46 -> 810 | D47: =D43+D46 -> 891 | E47: =E43+E46 -> 978 | F47: =F43+F46 -> 1073
A48: Equity | C48: 520 | D48: 523 | E48: 482 | F48: 377 | G48: Ex.2
A49: TOTAL LIABILITIES & EQUITY | C49: =C47+C48 -> 1330 | D49: =D47+D48 -> 1414 | E49: =E47+E48 -> 1460 | F49: =F47+F48 -> 1450
A50: Check: assets − liabilities & equity (should be 0) | C50: =C39-C49 -> 0 | D50: =D39-D49 -> 0 | E50: =E39-E49 -> 0 | F50: =F39-F49 -> 0
A52: Exhibit 3 — Segment financials
A53: USD m | C53: 2022 | D53: 2023 | E53: 2024 | F53: 2025
A54: Revenue — Auto Components | C54: 610 | D54: 630 | E54: 615 | F54: 570 | G54: Ex.3
A55: Revenue — Industrial Equipment & Machinery | C55: 350 | D55: 375 | E55: 400 | F55: 405 | G55: Ex.3
A56: Revenue — Specialty Materials & Coatings | C56: 190 | D56: 200 | E56: 215 | F56: 215 | G56: Ex.3
A57: Total segment revenue | C57: =SUM(C54:C56) -> 1150 | D57: =SUM(D54:D56) -> 1205 | E57: =SUM(E54:E56) -> 1230 | F57: =SUM(F54:F56) -> 1190
A58: EBITDA — Auto Components | C58: 68 | D58: 58 | E58: 30 | F58: 5 | G58: Ex.3. Direct project costs charged to segments; shared corporate & central digital costs allocated by revenue
A59: EBITDA — Industrial Equipment & Machinery | C59: 40 | D59: 42 | E59: 38 | F59: 33 | G59: Ex.3
A60: EBITDA — Specialty Materials & Coatings | C60: 14 | D60: 8 | E60: 2 | F60: -13 | G60: Ex.3
A61: Total segment EBITDA | C61: =SUM(C58:C60) -> 122 | D61: =SUM(D58:D60) -> 108 | E61: =SUM(E58:E60) -> 70 | F61: =SUM(F58:F60) -> 25
A63: Exhibit 4 — Cash flow and capital expenditure
A64: USD m (outflows negative) | C64: 2022 | D64: 2023 | E64: 2024 | F64: 2025
A65: Net income | D65: =D16 -> 11 | E65: =E16 -> -41 | F65: =F16 -> -105
A66: Add D&A | D66: =D11 -> 66 | E66: =E11 -> 78 | F66: =F11 -> 90
A67: Increase in operating working capital | D67: -9 | E67: -21 | F67: -11 | G67: Ex.4
A68: Operating cash flow after interest and tax | D68: =SUM(D65:D67) -> 68 | E68: =SUM(E65:E67) -> 16 | F68: =SUM(F65:F67) -> -26
A69: Maintenance PPE capex | D69: -45 | E69: -45 | F69: -45 | G69: Ex.4 — sustains existing operations; case asks to justify any reduction
A70: Physical upgrade and expansion capex | D70: -35 | E70: -30 | F70: -25 | G70: Ex.4
A71: Capitalised Factory of the Future spend | D71: -50 | E71: -55 | F71: -45 | G71: Ex.4
A72: Other intangible additions | D72: -10 | E72: 0 | F72: 0 | G72: Ex.4
A73: Total capital expenditure | D73: =SUM(D69:D72) -> -140 | E73: =SUM(E69:E72) -> -130 | F73: =SUM(F69:F72) -> -115
A74: Free cash flow before disposals | D74: =D68+D73 -> -72 | E74: =E68+E73 -> -114 | F74: =F68+F73 -> -141
A75: Other intangible disposal proceeds | D75: 0 | E75: 19 | F75: 31 | G75: Ex.4 — non-core licences sold at carrying value
A76: Net debt raised | D76: 65 | E76: 75 | F76: 85 | G76: Ex.4
A77: Dividends paid | D77: -8 | E77: 0 | F77: 0 | G77: Ex.4
A78: Net change in cash | D78: =D74+D75+D76+D77 -> -15 | E78: =E74+E75+E76+E77 -> -20 | F78: =F74+F75+F76+F77 -> -25
A79: Opening cash | D79: =C30 -> 90 | E79: =D30 -> 75 | F79: =E30 -> 55
A80: Closing cash | D80: =D79+D78 -> 75 | E80: =E79+E78 -> 55 | F80: =F79+F78 -> 30
A81: Check: closing cash − balance-sheet cash (should be 0) | D81: =D80-D30 -> 0 | E81: =E80-E30 -> 0 | F81: =F80-F30 -> 0
A82: Check: debt raised − change in total debt (should be 0) | D82: =D76-((D41+D44)-(C41+C44)) -> 0 | E82: =E76-((E41+E44)-(D41+D44)) -> 0 | F82: =F76-((F41+F44)-(E41+E44)) -> 0
A83: D&A — PPE | D83: 40 | E83: 45 | F83: 50 | G83: Ex.4 asset movement reconciliation
A84: D&A — digital & AI assets | D84: 15 | E84: 20 | F84: 25 | G84: Ex.4
A85: D&A — other intangibles | D85: 11 | E85: 13 | F85: 15 | G85: Ex.4
A86: Check: D&A split − total D&A (should be 0) | D86: =SUM(D83:D85)-D11 -> 0 | E86: =SUM(E83:E85)-E11 -> 0 | F86: =SUM(F83:F85)-F11 -> 0

Sheet Case_Digital
A1: Case data — digital programme (Exhibits 5–7, USD m)
A2: Columns: Predictive maintenance (PdM) · Computer-vision inspection (Vision) · Supply-chain planning (SCP) · Programme total.
A4: Exhibit 5 — Programme economics
A5: USD m | C5: PdM | D5: Vision | E5: SCP | F5: Total | G5: Source / note
A6: Capitalised spend 2023–25 | C6: 50 | D6: 55 | E6: 45 | F6: =SUM(C6:E6) -> 150 | G6: Ex.5
A7: Net assets at end-2025 | C7: 38 | D7: 44 | E7: 33 | F7: =SUM(C7:E7) -> 115 | G7: Ex.5
A8: 2025 operating cost (excl. D&A) | C8: 10 | D8: 12 | E8: 14 | F8: =SUM(C8:E8) -> 36 | G8: Ex.5
A9: 2025 gross benefit (realised, already in Cost of Sales) | C9: 5 | D9: 7 | E9: 1 | F9: =SUM(C9:E9) -> 13 | G9: Ex.5 — NOT an exit run-rate; must not be re-counted as future gain
A10: Requested capex, next 18 months (unapproved) | C10: 8 | D10: 12 | E10: 10 | F10: =SUM(C10:E10) -> 30 | G10: Ex.5 — excludes recurring opex and remaining implementation
A12: Exhibit 6 — 2025 project operating cost breakdown
A13: USD m | C13: PdM | D13: Vision | E13: SCP | F13: Total
A14: Software and platform licences | C14: 0.8 | D14: 1 | E14: 1.5 | F14: =SUM(C14:E14) -> 3.3 | G14: Ex.6 — recurring
A15: Cloud or edge compute and data storage | C15: 0.7 | D15: 1.2 | E15: 1.3 | F15: =SUM(C15:E15) -> 3.2 | G15: Ex.6 — recurring
A16: Metered language-model inference / tokens | C16: 0 | D16: 0 | E16: 0.8 | F16: =SUM(C16:E16) -> 0.8 | G16: Ex.6 — recurring; planning pilot only (agent calls)
A17: Monitoring, support and model maintenance | C17: 1.5 | D17: 1.8 | E17: 2.4 | F17: =SUM(C17:E17) -> 5.7 | G17: Ex.6 — recurring
A18: Recurring operating costs (subtotal) | C18: =SUM(C14:C17) -> 3 | D18: =SUM(D14:D17) -> 4 | E18: =SUM(E14:E17) -> 6 | F18: =SUM(C18:E18) -> 13
A19: Systems integration and data engineering | C19: 4 | D19: 4 | E19: 5 | F19: =SUM(C19:E19) -> 13 | G19: Ex.6 — temporary
A20: Data preparation, labelling, initial model validation | C20: 2 | D20: 3 | E20: 2 | F20: =SUM(C20:E20) -> 7 | G20: Ex.6 — temporary
A21: Training and change management | C21: 1 | D21: 1 | E21: 1 | F21: =SUM(C21:E21) -> 3 | G21: Ex.6 — temporary
A22: Temporary implementation costs (subtotal) | C22: =SUM(C19:C21) -> 7 | D22: =SUM(D19:D21) -> 8 | E22: =SUM(E19:E21) -> 8 | F22: =SUM(C22:E22) -> 23
A23: Total 2025 project operating cost | C23: =C18+C22 -> 10 | D23: =D18+D22 -> 12 | E23: =E18+E22 -> 14 | F23: =SUM(C23:E23) -> 36
A24: Check: Ex.6 total − Ex.5 operating cost (should be 0) | C24: =C23-C8 -> 0 | D24: =D23-D8 -> 0 | E24: =E23-E8 -> 0 | F24: =SUM(C24:E24) -> 0
A25: Committed recurring cost payable Jan–Dec 2026 | C25: 1 | D25: 1.5 | E25: 2 | F25: =SUM(C25:E25) -> 4.5 | G25: Ex.6 — payable even if deployment stops; included in recurring above
A26: Remaining expensed implementation work in 2026 | C26: 1 | D26: 2 | E26: 3 | F26: =SUM(C26:E26) -> 6 | G26: Ex.6 — required to continue CURRENT scope; excludes capex requests
A27: Shared central digital cost (annual) | C27: 12 | G27: Ex.6/Ex.8 — includes payroll of 24-person central team; stays in base case
A28: Central digital team (FTE) | C28: 24 | G28: Ex.8
A30: Exhibit 7 — Deployment and operational evidence (deployed scope only)
C31: PdM | D31: Vision | E31: SCP
A32: KPI | C32: Unplanned downtime (% sched. hrs) | D32: Scrap/rework (% covered-line cost) | E32: Pilot inventory days | G32: Ex.7
A33: Deployed scope (machines / lines / plants) | C33: 150 | D33: 8 | E33: 3 | G33: Ex.7 — PdM 150 machines (2 Auto + 1 IEM plant); Vision 8 lines (2 Auto + 1 SMC plant); SCP 3 plants (2 Auto + 1 IEM)
A34: Baseline | C34: 0.12 | D34: 0.06 | E34: 90 | G34: Ex.7
A35: Original business-case target | C35: 0.07 | D35: 0.035 | E35: 75 | G35: Ex.7 — targets, not achieved results
A36: 2025 outcome | C36: 0.09 | D36: 0.048 | E36: 94 | G36: Ex.7
A37: Adoption metric | C37: 0.6 | D37: 0.45 | E37: 0.35 | G37: Ex.7 — PdM: actionable alerts closed in window; Vision: flagged rejects needing manual review; SCP: schedules accepted without override
A38: On-time delivery (SCP pilot): baseline / 2025 | E38: 0.86 | G38: Ex.7 — 86% baseline, 86% in 2025 (no change)
A39: Reported constraint | C39: Maint. records, work-order integration, technicians | D39: Calibration on spec change; selected families only | E39: Master-data inconsistency; separate planning systems | G39: Ex.7

Sheet Case_Ops
A1: Case data — operating context (Exhibit 8)
A3: Manufacturing footprint and operating costs (2025)
C4: Auto | D4: IEM | E4: SMC | F4: Group | G4: Source / note
A5: Plants | C5: 5 | D5: 3 | E5: 3 | F5: =SUM(C5:E5) -> 11 | G5: Ex.8 — Auto: India 3, Vietnam 1, CE 1; IEM: India 1, Vietnam 1, CE 1; SMC: India 2, CE 1
A6: Capacity utilisation | C6: 0.72 | D6: 0.81 | E6: 0.67 | G6: Ex.8 — actual output / practical capacity at 2025 mix
A7: Energy expenditure (USD m, in Cost of Sales) | C7: 45 | D7: 25 | E7: 50 | F7: =SUM(C7:E7) -> 120 | G7: Ex.8
A8: Direct production labour (USD m, in Cost of Sales) | C8: 95 | D8: 60 | E8: 25 | F8: =SUM(C8:E8) -> 180 | G8: Ex.8
A9: Main processes | C9: Machining, forging, assembly | D9: Fabrication, machining, assembly | E9: Mixing, batch processing, coating | G9: Ex.8
A10: Principal customer requirements | C10: Accuracy, traceability, delivery, price | D10: Reliability, configurability, lead time, service | E10: Batch consistency, performance, tech support | G10: Ex.8
A12: Digital readiness
A13: Plants on shared ERP (of 11) | C13: 8 | G13: Ex.8 — 3 plants on local systems with monthly manual consolidation
A14: Production equipment with centrally accessible machine data | C14: 0.4 | G14: Ex.8 — rest on local logs/manual records; data definitions vary across plants

Sheet Diagnosis
A1: Diagnosis — what the exhibits say
A3: 1. Profitability, leverage and liquidity
C4: 2022 | D4: 2023 | E4: 2024 | F4: 2025 | H4: Reading
A5: Revenue growth | D5: =Case_Financials!$D$6/Case_Financials!$C$6-1 -> 0.047826087 | E5: =Case_Financials!$E$6/Case_Financials!$D$6-1 -> 0.020746888 | F5: =Case_Financials!$F$6/Case_Financials!$E$6-1 -> -0.032520325
A6: Gross margin | C6: =Case_Financials!$C$8/Case_Financials!$C$6 -> 0.25217391 | D6: =Case_Financials!$D$8/Case_Financials!$D$6 -> 0.24481328 | E6: =Case_Financials!$E$8/Case_Financials!$E$6 -> 0.23170732 | F6: =Case_Financials!$F$8/Case_Financials!$F$6 -> 0.21848739 | H6: Down ~3.4pp despite 13 of digital benefits inside 2025 COGS
A7: EBITDA margin | C7: =Case_Financials!$C$10/Case_Financials!$C$6 -> 0.10608696 | D7: =Case_Financials!$D$10/Case_Financials!$D$6 -> 0.089626556 | E7: =Case_Financials!$E$10/Case_Financials!$E$6 -> 0.056910569 | F7: =Case_Financials!$F$10/Case_Financials!$F$6 -> 0.021008403
A8: Opex (excl. D&A) / revenue | C8: =Case_Financials!$C$9/Case_Financials!$C$6 -> 0.14608696 | D8: =Case_Financials!$D$9/Case_Financials!$D$6 -> 0.15518672 | E8: =Case_Financials!$E$9/Case_Financials!$E$6 -> 0.17479675 | F8: =Case_Financials!$F$9/Case_Financials!$F$6 -> 0.19747899
A9: Digital & AI opex / revenue | C9: =Case_Financials!$C$24/Case_Financials!$C$6 -> 0.0069565217 | D9: =Case_Financials!$D$24/Case_Financials!$D$6 -> 0.014937759 | E9: =Case_Financials!$E$24/Case_Financials!$E$6 -> 0.028455285 | F9: =Case_Financials!$F$24/Case_Financials!$F$6 -> 0.040336134 | H9: Digital opex 6x since 2022 (8 → 48)
A10: Total debt (short + long term) | C10: =Case_Financials!$C$41+Case_Financials!$C$44 -> 560 | D10: =Case_Financials!$D$41+Case_Financials!$D$44 -> 625 | E10: =Case_Financials!$E$41+Case_Financials!$E$44 -> 700 | F10: =Case_Financials!$F$41+Case_Financials!$F$44 -> 785
A11: Net debt | C11: =C10-Case_Financials!$C$30 -> 470 | D11: =D10-Case_Financials!$D$30 -> 550 | E11: =E10-Case_Financials!$E$30 -> 645 | F11: =F10-Case_Financials!$F$30 -> 755
A12: Net debt / EBITDA | C12: =C11/Case_Financials!$C$10 -> 3.852459 | D12: =D11/Case_Financials!$D$10 -> 5.0925926 | E12: =E11/Case_Financials!$E$10 -> 9.2142857 | F12: =F11/Case_Financials!$F$10 -> 30.2 | H12: 30x in 2025 — ratings downgrade warning is unsurprising
A13: Interest cover (EBITDA / net finance costs) | C13: =Case_Financials!$C$10/Case_Financials!$C$13 -> 5.0833333 | D13: =Case_Financials!$D$10/Case_Financials!$D$13 -> 4 | E13: =Case_Financials!$E$10/Case_Financials!$E$13 -> 2.1212121 | F13: =Case_Financials!$F$10/Case_Financials!$F$13 -> 0.625 | H13: Below 1.0x: operating earnings no longer cover interest
A14: Implied interest rate (finance cost / average debt) | D14: =Case_Financials!$D$13/AVERAGE(C10,D10) -> 0.04556962 | E14: =Case_Financials!$E$13/AVERAGE(D10,E10) -> 0.049811321 | F14: =Case_Financials!$F$13/AVERAGE(E10,F10) -> 0.053872054 | H14: 2025 rate used to project interest (Assumptions)
A15: Short-term debt / total debt | C15: =Case_Financials!$C$41/C10 -> 0.16071429 | D15: =Case_Financials!$D$41/D10 -> 0.184 | E15: =Case_Financials!$E$41/E10 -> 0.20714286 | F15: =Case_Financials!$F$41/F10 -> 0.22929936 | H15: Refinancing risk rising: 180 due within 12 months vs 30 cash
A17: 2. Working capital
C18: 2022 | D18: 2023 | E18: 2024 | F18: 2025
A19: Operating working capital | C19: =Case_Financials!$C$31+Case_Financials!$C$32+Case_Financials!$C$33-Case_Financials!$C$40-Case_Financials!$C$42 -> 173 | D19: =Case_Financials!$D$31+Case_Financials!$D$32+Case_Financials!$D$33-Case_Financials!$D$40-Case_Financials!$D$42 -> 182 | E19: =Case_Financials!$E$31+Case_Financials!$E$32+Case_Financials!$E$33-Case_Financials!$E$40-Case_Financials!$E$42 -> 203 | F19: =Case_Financials!$F$31+Case_Financials!$F$32+Case_Financials!$F$33-Case_Financials!$F$40-Case_Financials!$F$42 -> 214 | H19: Ex.4 definition
A20: Check: Δ working capital + cash-flow line (should be 0) | D20: =(D19-C19)+Case_Financials!$D$67 -> 0 | E20: =(E19-D19)+Case_Financials!$E$67 -> 0 | F20: =(F19-E19)+Case_Financials!$F$67 -> 0
A21: Inventory days (inventory / COGS × 365) | C21: =Case_Financials!$C$32/Case_Financials!$C$7*365 -> 87.005814 | D21: =Case_Financials!$D$32/Case_Financials!$D$7*365 -> 88.241758 | E21: =Case_Financials!$E$32/Case_Financials!$E$7*365 -> 92.698413 | F21: =Case_Financials!$F$32/Case_Financials!$F$7*365 -> 100.08065 | H21: 87 → 100 days: ~33 of cash tied up vs 2022 level
A22: Receivable days (DSO) | C22: =Case_Financials!$C$31/Case_Financials!$C$6*365 -> 47.608696 | D22: =Case_Financials!$D$31/Case_Financials!$D$6*365 -> 47.858921 | E22: =Case_Financials!$E$31/Case_Financials!$E$6*365 -> 49.853659 | F22: =Case_Financials!$F$31/Case_Financials!$F$6*365 -> 52.756303
A23: Payable days (DPO) | C23: =Case_Financials!$C$40/Case_Financials!$C$7*365 -> 70.02907 | D23: =Case_Financials!$D$40/Case_Financials!$D$7*365 -> 71.395604 | E23: =Case_Financials!$E$40/Case_Financials!$E$7*365 -> 72.613757 | F23: =Case_Financials!$F$40/Case_Financials!$F$7*365 -> 76.532258 | H23: Not used as a lever: stretching suppliers during a downgrade is high-risk
A24: Cash conversion cycle (days) | C24: =C21+C22-C23 -> 64.58544 | D24: =D21+D22-D23 -> 64.705075 | E24: =E21+E22-E23 -> 69.938315 | F24: =F21+F22-F23 -> 76.30469
A26: 3. Segment EBITDA margins
C27: 2022 | D27: 2023 | E27: 2024 | F27: 2025
A28: Auto Components | C28: =Case_Financials!$C$58/Case_Financials!$C$54 -> 0.11147541 | D28: =Case_Financials!$D$58/Case_Financials!$D$54 -> 0.092063492 | E28: =Case_Financials!$E$58/Case_Financials!$E$54 -> 0.048780488 | F28: =Case_Financials!$F$58/Case_Financials!$F$54 -> 0.0087719298 | H28: 11.1% → 0.9%: in forced-sale territory
A29: Industrial Equipment & Machinery | C29: =Case_Financials!$C$59/Case_Financials!$C$55 -> 0.11428571 | D29: =Case_Financials!$D$59/Case_Financials!$D$55 -> 0.112 | E29: =Case_Financials!$E$59/Case_Financials!$E$55 -> 0.095 | F29: =Case_Financials!$F$59/Case_Financials!$F$55 -> 0.081481481 | H29: Growing; the healthiest business
A30: Specialty Materials & Coatings | C30: =Case_Financials!$C$60/Case_Financials!$C$56 -> 0.073684211 | D30: =Case_Financials!$D$60/Case_Financials!$D$56 -> 0.04 | E30: =Case_Financials!$E$60/Case_Financials!$E$56 -> 0.0093023256 | F30: =Case_Financials!$F$60/Case_Financials!$F$56 -> -0.060465116 | H30: Loss-making; energy is 23% of revenue
A32: 4. EBITDA bridge 2022 → 2025
A33: USD m | C33: Impact | D33: % of decline
A34: EBITDA 2022 | C34: =Case_Financials!$C$10 -> 122
A35: Underlying gross-profit erosion (excl. digital benefits) | C35: =(Case_Financials!$F$8-Case_Financials!$C$8)-Case_Digital!$F$9 -> -43 | D35: =C35/(C41-C34) -> 0.44329897 | H35: OEM pricing, input & energy costs, mix — the COO and Auto sales head are both right
A36: Digital gross benefits realised in COGS (2025) | C36: =Case_Digital!$F$9 -> 13 | D36: =C36/(C41-C34) -> -0.13402062
A37: Increase in digital & AI opex | C37: =-(Case_Financials!$F$24-Case_Financials!$C$24) -> -40 | D37: =C37/(C41-C34) -> 0.41237113 | H37: Single largest controllable driver
A38: Increase in non-digital personnel | C38: =-(Case_Financials!$F$22-Case_Financials!$C$22) -> -18 | D38: =C38/(C41-C34) -> 0.18556701
A39: Increase in selling & customer support | C39: =-(Case_Financials!$F$23-Case_Financials!$C$23) -> -10 | D39: =C39/(C41-C34) -> 0.10309278
A40: Change in other overheads | C40: =-(Case_Financials!$F$25-Case_Financials!$C$25) -> 1 | D40: =C40/(C41-C34) -> -0.010309278
A41: EBITDA 2025 | C41: =SUM(C34:C40) -> 25
A42: Check: bridge end − reported 2025 EBITDA (should be 0) | C42: =C41-Case_Financials!$F$10 -> 0
A43: Memo: segment EBITDA change — Auto | C43: =Case_Financials!$F$58-Case_Financials!$C$58 -> -63 | D43: =C43/(C41-C34) -> 0.64948454 | H43: Auto explains ~2/3 of the Group decline
A44: Memo: segment EBITDA change — IEM | C44: =Case_Financials!$F$59-Case_Financials!$C$59 -> -7 | D44: =C44/(C41-C34) -> 0.072164948
A45: Memo: segment EBITDA change — SMC | C45: =Case_Financials!$F$60-Case_Financials!$C$60 -> -27 | D45: =C45/(C41-C34) -> 0.27835052
A47: 5. Factory of the Future scorecard (2025)
A48: USD m | C48: PdM | D48: Vision | E48: SCP | F48: Programme
A49: 2025 operating cost | C49: =Case_Digital!$C$8 -> 10 | D49: =Case_Digital!$D$8 -> 12 | E49: =Case_Digital!$E$8 -> 14 | F49: =Case_Digital!$F$8 -> 36
A50: of which recurring | C50: =Case_Digital!$C$18 -> 3 | D50: =Case_Digital!$D$18 -> 4 | E50: =Case_Digital!$E$18 -> 6 | F50: =Case_Digital!$F$18 -> 13
A51: of which temporary implementation | C51: =Case_Digital!$C$22 -> 7 | D51: =Case_Digital!$D$22 -> 8 | E51: =Case_Digital!$E$22 -> 8 | F51: =Case_Digital!$F$22 -> 23
A52: 2025 gross benefit | C52: =Case_Digital!$C$9 -> 5 | D52: =Case_Digital!$D$9 -> 7 | E52: =Case_Digital!$E$9 -> 1 | F52: =Case_Digital!$F$9 -> 13
A53: Net 2025 P&L effect (benefit − operating cost) | C53: =C52-C49 -> -5 | D53: =D52-D49 -> -5 | E53: =E52-E49 -> -13 | F53: =F52-F49 -> -23
A54: Net recurring effect (benefit − recurring cost) | C54: =C52-C50 -> 2 | D54: =D52-D50 -> 3 | E54: =E52-E50 -> -5 | F54: =F52-F50 -> 0 | H54: PdM and Vision pay their running costs; SCP does not
A55: Benefit per $ of recurring cost | C55: =C52/C50 -> 1.6666667 | D55: =D52/D50 -> 1.75 | E55: =E52/E50 -> 0.16666667 | F55: =F52/F50 -> 1
A56: Share of targeted KPI improvement achieved | C56: =(Case_Digital!$C$34-Case_Digital!$C$36)/(Case_Digital!$C$34-Case_Digital!$C$35) -> 0.6 | D56: =(Case_Digital!$D$34-Case_Digital!$D$36)/(Case_Digital!$D$34-Case_Digital!$D$35) -> 0.48 | E56: =(Case_Digital!$E$34-Case_Digital!$E$36)/(Case_Digital!$E$34-Case_Digital!$E$35) -> -0.26666667 | H56: PdM 60%, Vision 48%; SCP negative — inventory days rose 90 → 94
A57: Capitalised spend 2023–25 | C57: =Case_Digital!$C$6 -> 50 | D57: =Case_Digital!$D$6 -> 55 | E57: =Case_Digital!$E$6 -> 45 | F57: =Case_Digital!$F$6 -> 150
A58: Years of net recurring benefit to recover capitalised spend | C58: =IF(C54>0,C57/C54,"never") -> 25 | D58: =IF(D54>0,D57/D54,"never") -> 18.333333 | E58: =IF(E54>0,E57/E54,"never") -> never | H58: At current scope, even the winners take 18–25 years: scale and adoption are the issue, not the technology
A59: Total digital & AI opex 2025 (projects + central) | C59: =Case_Digital!$F$8+Case_Digital!$C$27 -> 48 | H59: 36 project + 12 shared central
A60: Check: vs Ex.1 digital opex (should be 0) | C60: =C59-Case_Financials!$F$24 -> 0
A61: Net digital P&L 2025 (benefits − all digital opex) | C61: =Case_Digital!$F$9-C59 -> -35 | H61: Digital is currently a −35 drag on a 25 EBITDA business
A63: 6. What improves automatically in 2026 (not claimed as our impact)
A64: 2025 temporary implementation cost | C64: =Case_Digital!$F$22 -> 23
A65: Remaining implementation work required in 2026 (current scope) | C65: =Case_Digital!$F$26 -> 6
A66: Automatic 2026 EBITDA roll-off vs 2025 | C66: =C64-C65 -> 17 | H66: Temporary costs do not recur (Ex.6). Base case gets this too — our plan must beat it
A68: 7. How much of Auto's collapse is digital? (allocation assumption)
A69: Pilot project opex borne by Auto | C69: =Case_Digital!$F$8*Assumptions!$C$7 -> 24 | H69: Pilots sit in 2 Auto plants of 3 per project → 2/3 share (assumption)
A70: Central digital cost allocated to Auto (by revenue) | C70: =Case_Digital!$C$27*Case_Financials!$F$54/Case_Financials!$F$6 -> 5.7478992 | H70: Ex.3 allocation rule
A71: Digital benefits accruing to Auto | C71: =Case_Digital!$F$9*Assumptions!$C$7 -> 8.6666667
A72: Net digital drag on Auto EBITDA | C72: =C71-C69-C70 -> -21.081232
A73: Auto EBITDA excluding net digital drag | C73: =Case_Financials!$F$58-C72 -> 26.081232
A74: Auto EBITDA margin excluding net digital drag | C74: =C73/Case_Financials!$F$54 -> 0.045756548 | H74: Still far below 11.1% in 2022 → the rest is pricing/volume/input cost: digital must reach commercial & procurement
A76: 8. Consistency flag — Vision benefit vs scrap reduction
A77: Implied covered-line production cost (benefit ÷ scrap-point reduction) | C77: =Case_Digital!$D$9/(Case_Digital!$D$34-Case_Digital!$D$36) -> 583.33333 | H77: 7.0 ÷ 1.2% ≈ 583
A78: Implied share of Group cost of sales on 8 lines | C78: =C77/Case_Financials!$F$7 -> 0.62724014 | H78: Implausible for 8 lines → benefit likely includes inspection-labour savings. We do NOT extrapolate this ratio; new lines are haircut 50%

Sheet Assumptions
A1: Assumptions — every judgement call in one place
A2: Blue = our assumption (edit to test). Yellow = key driver. Green = linked from case data. [Bx] codes point to the Sources tab.
A4: Assumption | B4: Unit | C4: Value | D4: Rationale / benchmark
A5: General
A6: Benefit realisation factor (base case) | C6: 0.75 | D6: Pilots achieved 48–60% of targeted KPI gains (Ex.7); benchmark levers are already sized well below published ranges → 75% sits between. 100% = stretch, 50% = downside (Sensitivity). Not applied to F3 (contractual cost removal)
A7: Auto share of pilot project cost & benefit | C7: 0.66666667 | D7: Each pilot runs in 2 Auto plants out of 3 (Ex.7); allocation by plant count
A8: Incremental recurring cost per unit when scaling, vs pilot per-unit cost | C8: 0.67 | D8: Platform licences, monitoring and team are shared, so scaling costs less than the pilot per unit
A9: Interest rate on debt (before refinancing premium) | C9: =Diagnosis!$F$14 -> 0.053872054 | D9: 2025 implied: 40 ÷ average debt of 742 (Diagnosis). Applied to opening debt each period (avoids circularity)
A10: Refinancing premium on rolled-over short-term debt and all new money | C10: 0.03 | D10: Assumption: +300bp for a borrower on downgrade watch; applied from Jan-26 to the 180 of short-term debt and to every dollar of new borrowing
A11: Minimum cash balance | C11: 30 | D11: Held at the 2025 closing level; any shortfall is funded by debt
A12: Cash tax | C12: 0 | D12: PBT stays negative through Jun-27 in every case (checked on Projection); no cash tax
A13: D&A per year (for PBT check only) | C13: =Case_Financials!$F$11 -> 90 | D13: Held at 2025 level; used only to confirm PBT < 0
A14: Steady-state digital capex per year after the mandate | C14: 10 | D14: Used only for the run-rate cash break-even test
A15: Revenue and underlying gross margin held at 2025 levels | C15: Held | D15: No market recovery and no further erosion assumed. OEM price-down and volume risks shown on Sensitivity
A16: Base case (momentum: current scope continues, capex requests approved as submitted)
A17: Base: upgrade & expansion capex per year | C17: 25 | D17: 2025 level (Ex.4)
A18: Base: digital capex over 18 months | C18: =Case_Digital!$F$10 -> 30 | D18: All three requests approved (8 + 12 + 10; Ex.5)
A19: Base: share of 18-month digital capex spent in 2026 | C19: 0.66666667 | D19: Straight-line over 18 months
A20: Capex policy (plan)
A21: Maintenance capex per year (plan and base) | C21: 45 | D21: NOT reduced: already below PPE depreciation of 50 (Ex.4); case requires justification for any cut
A22: Plan: upgrade & expansion capex per year | C22: 10 | D22: Defer expansion: utilisation is 72% Auto, 81% IEM, 67% SMC (Ex.8), so no business is capacity-constrained. Keep 10 for safety/debottlenecking
A23: W1 Foundations
A24: F1 Master data & ERP harmonisation: capex | C24: 10 | D24: Redirect the SCP capex request (10) to move the 3 local-system plants onto the shared ERP in waves + master-data tooling
A25: F1: one-off implementation opex | C25: 3 | D25: Uses the SCP remaining-work budget (3.0), repurposed to data cleansing and governance
A26: F1: recurring cost (data stewards, MDM tool) | C26: 0.5 | D26: Assumption: ~5 data stewards across plants + MDM licence
A27: F2 Digital Value Office: recurring cost | C27: 1 | D27: Chief Digital Officer reporting to CEO + 4 business product owners + value tracking; central team of 24 reallocated, not added
A28: F2: one-off change management & training | C28: 0.5 | D28: Plant digital-champion network, adoption training
A29: F3 SCP descope: licences retained | C29: 1 | D29: Keep the core planning tool so planners keep working and data fixes can be tested
A30: F3: cloud/compute retained | C30: 0.5 | D30: Smaller footprint once agent layer is off
A31: F3: language-model tokens retained | C31: 0 | D31: Switch off the agentic layer: 35% acceptance, inventory days worse (Ex.7)
A32: F3: monitoring & model maintenance retained | C32: 0.4 | D32: Fewer models to maintain
A33: F3: one-off transition / shutdown cost | C33: 0.5 | D33: Case requires an explicit assumption (Ex.6). 2026 commitments (2.0) are below the retained run-cost (3.1) and lapse without penalty from Jan-27
A34: W2 Maintenance · W3 Quality (fix and scale what works)
A35: S1 PdM current cohort: target downtime by Jun-27 | C35: 0.075 | D35: 12% → 7.5% = 37.5% reduction, inside McKinsey's 30–50% range [B1]; short of the 7% business-case target given technician constraints
A36: S1: recurring cost (technician capacity, work-order integration upkeep) | C36: 0.5 | D36: Close the loop: alerts closed in window 60% → 85% (month-6 gate)
A37: S2 PdM scale-up: additional connected assets | C37: 150 | D37: Doubles the cohort, IEM-led (81% utilisation, growing); released only after the S1 gate
A38: S2: benefit per asset vs pilot | C38: 0.7 | D38: Haircut for new plants and lower data readiness (40% machine-data coverage, Ex.8)
A39: S2: share of new assets in Auto | C39: 0.3 | D39: Rest in IEM
A40: S2: one-off implementation opex | C40: 2 | D40: Integration + model tuning for new assets
A41: S2: capex | C41: =Case_Digital!$C$10 -> 8 | D41: Approve the PdM request (Ex.5), released in tranches after the gate
A42: S3 Vision current lines: target scrap/rework by Jun-27 | C42: 0.042 | D42: 6.0% → 4.2% = 72% of targeted improvement (vs 48% today) via retraining and a calibration workflow for spec changes
A43: S3: one-off retraining / calibration workflow | C43: 0.5 | D43: Remaining 2026 work (2.0) is already in the base case
A44: S4 Vision + traceability: additional Auto lines (gated, one named OEM programme) | C44: 3 | D44: Only where an OEM programme demands part-level traceability; capex released after month-9 gate. EBITDA-neutral — justified as customer retention, so kept small
A45: S4: benefit per line vs pilot average | C45: 0.5 | D45: Pilot ratio implies implausible covered cost (Diagnosis §8) → 50% haircut
A46: S4: one-off implementation opex | C46: 0.8 | D46: Stations, calibration for new part families
A47: S4: capex | C47: 4 | D47: Cut the 12 request to 4: three Auto lines for one OEM programme
A48: W4 Energy & process · W5 Procurement · W6 Commercial & back-office · W7 Service growth
A49: N1 Energy management: saving on Auto energy (forging) | C49: 0.06 | D49: Sub-metering + load scheduling + furnace optimisation. ISO 50001 plants ~4.1% in year 1 [B3]; APC up to 10% energy reduction [B2]
A50: N1: saving on IEM energy | C50: 0.03 | D50: Less energy-intensive assembly; lower target
A51: N1: saving on SMC energy | C51: 0.06 | D51: Batch heating/curing: energy is 23% of SMC revenue (Ex.8)
A52: N1: recurring cost (energy platform, analyst) | C52: 0.8
A53: N1: one-off implementation opex | C53: 1
A54: N1: capex (sub-metering, controls) | C54: 3 | D54: Needed: only 40% of equipment has central machine data (Ex.8)
A55: N2 SMC golden-batch / process control: yield gain on SMC materials & other cost | C55: 0.02 | D55: APC delivers up to 5% yield [B2]. Sized on materials only (energy excluded) → no overlap with N1. Funded only if SMC passes the month-6 gate
A56: N2: recurring cost | C56: 0.4
A57: N2: one-off implementation opex | C57: 0.8
A58: N2: capex (process sensors) | C58: 2
A59: N3 Procurement analytics: addressable share of non-energy, non-labour COGS | C59: 0.7 | D59: COGS 930 − energy 120 − labour 180 = 630; ~70% is bought-in materials & parts (assumption)
A60: N3: net saving on addressable spend | C60: 0.0125 | D60: Far below the 6–12% McKinsey observes in chemicals procurement [B4]
A61: N3: recurring cost (spend-cube tool, 2 analysts) | C61: 0.5
A62: N3: one-off implementation opex | C62: 1
A63: N4 Commercial: index-linked cost pass-through, Auto | C63: 0.005 | D63: NOT a list-price rise: inserts energy/raw-material index clauses at named OEM contract renewals, recovering inflation Ironbridge absorbed. Pricing programmes add 2–7pp ROS [B5]
A64: N4: price realisation, IEM (configure-price-quote) | C64: 0.005 | D64: Configuration flexibility is valued (Ex.8); CPQ cuts quote lead time and discount leakage
A65: N4: price realisation, SMC (cost pass-through, specialty value pricing) | C65: 0.01 | D65: SMC EBITDA fell 15 in 2025 on flat revenue → energy/input inflation not passed on. Specialty coatings carry more pricing power than auto parts
A66: N4: recurring cost (pricing analysts, CPQ licence) | C66: 0.7 | D66: Covers all three businesses
A67: N4: one-off implementation opex | C67: 1
A68: N5 IEM connected-service pilot: service revenue as % of IEM revenue by Jun-27 | C68: 0.01 | D68: Remote monitoring + predictive service on installed pumps/drives, reusing the PdM stack
A69: N5: EBITDA margin on service revenue | C69: 0.2 | D69: Aftermarket services average 25% EBIT vs 10% for new equipment [B6]; haircut for start-up
A70: N5: one-off (offer design, pilot contracts) | C70: 1
A71: N5: capex (sensor kits for pilot fleet) | C71: 2
A72: N6 Back-office & customer-support automation: addressable cost | C72: =Case_Financials!$F$22+Case_Financials!$F$23 -> 153 | D72: Non-digital personnel (108) + selling & customer support (45): up 28 since 2022 while revenue rose 3.5% (Ex.1)
A73: N6: productivity saving on addressable cost | C73: 0.04 | D73: GenAI in customer care: 30–45% of function cost [B8]; automation of the 3 plants' manual month-end consolidation (Ex.8). Delivered via attrition and hiring freeze
A74: N6: recurring cost (GenAI licences, tokens, automation upkeep) | C74: 1 | D74: Token spend budgeted explicitly — the SCP lesson (Ex.6)
A75: N6: one-off implementation opex | C75: 1
A76: Overlap netting (so benefits are not double-counted)
A77: O2: share of Auto procurement savings passed back to OEMs | C77: 0.5 | D77: Index-linked clauses work both ways: cheaper indexed materials flow through to OEM prices. Applied to Auto's revenue share of N3
A78: O3: share of Auto productivity savings conceded in OEM annual price-downs | C78: 0.25 | D78: Auto OEMs typically ask for annual productivity give-backs; applied to Auto's share of PdM, vision and energy savings
A79: Working capital (plan) — phased after the master-data fix
A80: Inventory days — Dec-26 | C80: 96 | D80: From 100. 2026: slow-mover clean-up and safety-stock reset only (does not need the planning tool)
A81: Inventory days — Jun-27 | C81: 90 | D81: After F1 master data: 2023 level was 88. A 10% cut vs 30% achieved in a McKinsey SC case [B7]
A82: Receivable days (DSO) — Dec-26 | C82: 51 | D82: From 52.8. E-invoicing, collections analytics, dispute resolution
A83: Receivable days (DSO) — Jun-27 | C83: 49 | D83: 2023 level was 47.9
A84: Funding bridge (balance-sheet actions, outside the digital numbers)
A85: Further non-core licence disposals | C85: 20 | D85: Precedent in the case: non-core licences sold at carrying value — 19 (2024), 31 (2025); 113 of other intangibles remain (Ex.2, Ex.4)
A86: Sale-and-leaseback of selected plant property | C86: 40 | D86: Assumption: ~6% of 680 net PPE. Creates a lease liability: buys liquidity, not deleveraging
A87: Supply-chain finance / non-recourse receivables factoring | C87: 25 | D87: Assumption: ~15% of 172 receivables, on OEM-backed programmes
A88: Sensitivity inputs
A89: Auto contribution margin (for volume shocks) | C89: 0.25 | D89: Assumption: materials, energy and ~half of direct labour vary with volume
A90: Win condition — what "turned around by Jun-27" means (tests a board and its lenders would apply)
A91: Liquidity: new money needed beyond rolling the 180 and identified sources — at most | C91: 0 | D91: The company can fund the mandate without asking lenders for fresh money (2025: FCF −141)
A92: Solvency: exit run-rate interest cover in the DOWNSIDE case (50% realisation) — at least | C92: 1 | D92: Earnings cover interest again even if only half the benefits land (2025: 0.6x)
A93: Auto plants' share of maintenance capex (5 of 11 plants) | C93: =Assumptions!$C$21*Case_Ops!$C$5/Case_Ops!$F$5 -> 20.454545 | D93: Proxy for the capex Auto needs to stand still; allocation by plant count (assumption)
A94: Digital: net digital contribution at Jun-27 run-rate — above | C94: 0 | D94: Digital pays for itself (2025: −35)

Sheet Initiatives
A1: Initiatives — run-rate economics, phasing, workstreams and segment split
A2: Part A derives each lever's annual run-rate at June 2027 from Assumptions. Part B applies the realisation factor and phases it over the mandate. Ramps are % of annual run-rate achieved on average in the period.
A4: Part A — Run-rate derivation (USD m, annual at Jun-27, before realisation factor)
A5: Initiative | B5: Workstream | C5: Gross benefit | D5: Recurring cost | E5: One-off opex (18m) | F5: Capex (18m) | G5: Revenue added | H5: Realisation applies (1/0) | Y5: How the benefit is calculated
A6: F1 · Master data & ERP harmonisation (3 plants, in waves) | B6: W1 Foundations | C6: 0 | D6: =Assumptions!$C$26 -> 0.5 | E6: =Assumptions!$C$25 -> 3 | F6: =Assumptions!$C$24 -> 10 | G6: 0 | H6: 1 | Y6: Enabler: unlocks the 2027 inventory release, procurement analytics and any later planning automation
A7: F2 · Digital Value Office & Chief Digital Officer | B7: W1 Foundations | C7: 0 | D7: =Assumptions!$C$27 -> 1 | E7: =Assumptions!$C$28 -> 0.5 | F7: 0 | G7: 0 | H7: 1 | Y7: Enabler: business-owned use cases, numeric stage-gates, value tracking
A8: F3 · Switch off SCP agentic layer; keep core planning tool | B8: W1 Foundations | C8: =Case_Digital!$E$14*(1-Assumptions!$C$29)+Case_Digital!$E$15*(1-Assumptions!$C$30)+Case_Digital!$E$16*(1-Assumptions!$C$31)+Case_Digital!$E$17*(1-Assumptions!$C$32) -> 2.89 | D8: 0 | E8: =Assumptions!$C$33-Case_Digital!$E$26 -> -2.5 | F8: 0 | G8: 0 | H8: 0 | Y8: Avoided SCP recurring cost (contractual, so no realisation haircut). One-off negative: remaining SCP work (3.0) avoided, net of 0.5 transition
A9: S1 · PdM: close the loop on current 150 machines | B9: W2 Maintenance | C9: =(Case_Digital!$C$36-Assumptions!$C$35)*Case_Digital!$C$9/(Case_Digital!$C$34-Case_Digital!$C$36) -> 2.5 | D9: =Assumptions!$C$36 -> 0.5 | E9: 0 | F9: 0 | G9: 0 | H9: 1 | Y9: Pilot benefit per downtime point (5.0 ÷ 3pt) × further points (9.0% → 7.5%)
A10: S2 · PdM: scale to +150 assets (IEM-led, gated) | B10: W2 Maintenance | C10: =Assumptions!$C$37*Case_Digital!$C$9/Case_Digital!$C$33*Assumptions!$C$38 -> 3.5 | D10: =Assumptions!$C$37*Case_Digital!$C$18/Case_Digital!$C$33*Assumptions!$C$8 -> 2.01 | E10: =Assumptions!$C$40 -> 2 | F10: =Assumptions!$C$41 -> 8 | G10: 0 | H10: 1 | Y10: Pilot benefit per machine (5.0 ÷ 150) × assets × 70%; cost per machine (3.0 ÷ 150) × 67%
A11: S3 · Vision: retrain & calibrate current 8 lines | B11: W3 Quality | C11: =(Case_Digital!$D$36-Assumptions!$C$42)*Case_Digital!$D$9/(Case_Digital!$D$34-Case_Digital!$D$36) -> 3.5 | D11: 0 | E11: =Assumptions!$C$43 -> 0.5 | F11: 0 | G11: 0 | H11: 1 | Y11: Pilot benefit per scrap point on the SAME lines (7.0 ÷ 1.2pt) × further points (4.8% → 4.2%)
A12: S4 · Vision + traceability: +3 Auto lines (gated) | B12: W3 Quality | C12: =Assumptions!$C$44*Case_Digital!$D$9/Case_Digital!$D$33*Assumptions!$C$45 -> 1.3125 | D12: =Assumptions!$C$44*Case_Digital!$D$18/Case_Digital!$D$33*Assumptions!$C$8 -> 1.005 | E12: =Assumptions!$C$46 -> 0.8 | F12: =Assumptions!$C$47 -> 4 | G12: 0 | H12: 1 | Y12: Pilot benefit per line (7.0 ÷ 8) × 50% haircut; cost per line (4.0 ÷ 8) × 67%. Justified mainly by OEM traceability
A13: N1 · Energy management & optimisation | B13: W4 Energy & process | C13: =Case_Ops!$C$7*Assumptions!$C$49+Case_Ops!$D$7*Assumptions!$C$50+Case_Ops!$E$7*Assumptions!$C$51 -> 6.45 | D13: =Assumptions!$C$52 -> 0.8 | E13: =Assumptions!$C$53 -> 1 | F13: =Assumptions!$C$54 -> 3 | G13: 0 | H13: 1 | Y13: Segment energy spend (Ex.8) × saving %
A14: N2 · SMC golden-batch & process control (gated) | B14: W4 Energy & process | C14: =Assumptions!$C$55*(Case_Financials!$F$56*Case_Financials!$F$7/Case_Financials!$F$6-Case_Ops!$E$7-Case_Ops!$E$8) -> 1.8605042 | D14: =Assumptions!$C$56 -> 0.4 | E14: =Assumptions!$C$57 -> 0.8 | F14: =Assumptions!$C$58 -> 2 | G14: 0 | H14: 1 | Y14: SMC COGS proxied at Group COGS/revenue ratio, less SMC energy & labour → materials ≈ 93; × 2% yield
A15: N3 · Procurement spend analytics & should-cost | B15: W5 Procurement | C15: =(Case_Financials!$F$7-Case_Ops!$F$7-Case_Ops!$F$8)*Assumptions!$C$59*Assumptions!$C$60 -> 5.5125 | D15: =Assumptions!$C$61 -> 0.5 | E15: =Assumptions!$C$62 -> 1 | F15: 0 | G15: 0 | H15: 1 | Y15: (930 − 120 − 180) × 70% addressable × 1.25%
A16: N4 · Cost pass-through & quoting (index clauses, CPQ) | B16: W6 Commercial & back-office | C16: =Case_Financials!$F$54*Assumptions!$C$63+Case_Financials!$F$55*Assumptions!$C$64+Case_Financials!$F$56*Assumptions!$C$65 -> 7.025 | D16: =Assumptions!$C$66 -> 0.7 | E16: =Assumptions!$C$67 -> 1 | F16: 0 | G16: =Case_Financials!$F$54*Assumptions!$C$63+Case_Financials!$F$55*Assumptions!$C$64+Case_Financials!$F$56*Assumptions!$C$65 -> 7.025 | H16: 1 | Y16: Segment revenue × price realisation (Auto 0.5%, IEM 0.5%, SMC 1.0%)
A17: N6 · Back-office & customer-support automation | B17: W6 Commercial & back-office | C17: =Assumptions!$C$72*Assumptions!$C$73 -> 6.12 | D17: =Assumptions!$C$74 -> 1 | E17: =Assumptions!$C$75 -> 1 | F17: 0 | G17: 0 | H17: 1 | Y17: (108 personnel + 45 selling & support) × 4%
A18: N5 · IEM connected-service pilot ("predictive service") | B18: W7 Service growth | C18: =Case_Financials!$F$55*Assumptions!$C$68*Assumptions!$C$69 -> 0.81 | D18: 0 | E18: =Assumptions!$C$70 -> 1 | F18: =Assumptions!$C$71 -> 2 | G18: =Case_Financials!$F$55*Assumptions!$C$68 -> 4.05 | H18: 1 | Y18: IEM revenue × 1% service revenue × 20% margin — a growth option more than a 2027 profit driver
A19: O2 · Less: procurement savings passed to OEMs | B19: Overlap netting | C19: =-Assumptions!$C$77*C15*Case_Financials!$F$54/Case_Financials!$F$6 -> -1.3202206 | D19: 0 | E19: 0 | F19: 0 | G19: 0 | H19: 1 | Y19: Index-linked contracts hand back part of Auto's share of N3
A20: O3 · Less: OEM productivity give-backs | B20: Overlap netting | C20: =-Assumptions!$C$78*(C9*Assumptions!$C$7+C10*Assumptions!$C$39+C11*Assumptions!$C$7+C12+Case_Ops!$C$7*Assumptions!$C$49) -> -2.265625 | D20: 0 | E20: 0 | F20: 0 | G20: 0 | H20: 1 | Y20: Share of Auto's PdM, vision and energy savings conceded in annual price-downs
A21: Total | C21: =SUM(C6:C20) -> 37.894659 | D21: =SUM(D6:D20) -> 8.415 | E21: =SUM(E6:E20) -> 10.1 | F21: =SUM(F6:F20) -> 29 | G21: =SUM(G6:G20) -> 11.075
A22: of which gross benefit subject to realisation | C22: =SUMPRODUCT(C6:C20,H6:H20) -> 35.004659
A23: of which gross benefit not subject to realisation | C23: =C21-C22 -> 2.89
A25: Part B — Phasing over the mandate (Jan-26 to Jun-27) and segment split — after realisation factor
A26: Initiative | B26: Workstream | C26: Benefit RR | D26: Cost RR | E26: Net RR | F26: Ben. ramp 2026 | G26: Ben. ramp H1-27 | H26: Cost ramp 2026 | I26: Cost ramp H1-27 | J26: One-off 18m | K26: One-off % 2026 | L26: Capex 18m | M26: Capex % 2026 | N26: EBITDA 2026 | O26: EBITDA H1-27 | P26: EBITDA 18m | Q26: Capex 2026 | R26: Capex H1-27 | S26: Feasibility (1–5) | T26: Months to value | U26: Auto | V26: IEM | W26: SMC | X26: Split check | Y26: Phasing rationale
A27: =A6 -> F1 · Master data & ERP harmonisation (3 plants, in waves) | B27: =B6 -> W1 Foundations | C27: =C6*IF(H6=1,Assumptions!$C$6,1) -> 0 | D27: =D6 -> 0.5 | E27: =C27-D27 -> -0.5 | F27: 0 | G27: 0 | H27: 0.4 | I27: 1 | J27: =E6 -> 3 | K27: 0.6 | L27: =F6 -> 10 | M27: 0.6 | N27: =C27*F27-D27*H27-J27*K27 -> -2 | O27: =0.5*(C27*G27-D27*I27)-J27*(1-K27) -> -1.45 | P27: =N27+O27 -> -3.45 | Q27: =L27*M27 -> 6 | R27: =L27-Q27 -> 4 | S27: 3 | T27: 9 | U27: =Case_Financials!$F$54/Case_Financials!$F$6 -> 0.4789916 | V27: =Case_Financials!$F$55/Case_Financials!$F$6 -> 0.34033613 | W27: =Case_Financials!$F$56/Case_Financials!$F$6 -> 0.18067227 | X27: =U27+V27+W27 -> 1 | Y27: ERP cut-over in waves, months 4–16; no P&L inside the window — the base for 2027+
A28: =A7 -> F2 · Digital Value Office & Chief Digital Officer | B28: =B7 -> W1 Foundations | C28: =C7*IF(H7=1,Assumptions!$C$6,1) -> 0 | D28: =D7 -> 1 | E28: =C28-D28 -> -1 | F28: 0 | G28: 0 | H28: 0.9 | I28: 1 | J28: =E7 -> 0.5 | K28: 0.7 | L28: =F7 -> 0 | M28: 0 | N28: =C28*F28-D28*H28-J28*K28 -> -1.25 | O28: =0.5*(C28*G28-D28*I28)-J28*(1-K28) -> -0.65 | P28: =N28+O28 -> -1.9 | Q28: =L28*M28 -> 0 | R28: =L28-Q28 -> 0 | S28: 5 | T28: 1 | U28: =Case_Financials!$F$54/Case_Financials!$F$6 -> 0.4789916 | V28: =Case_Financials!$F$55/Case_Financials!$F$6 -> 0.34033613 | W28: =Case_Financials!$F$56/Case_Financials!$F$6 -> 0.18067227 | X28: =U28+V28+W28 -> 1 | Y28: Stood up in month 1
A29: =A8 -> F3 · Switch off SCP agentic layer; keep core planning tool | B29: =B8 -> W1 Foundations | C29: =C8*IF(H8=1,Assumptions!$C$6,1) -> 2.89 | D29: =D8 -> 0 | E29: =C29-D29 -> 2.89 | F29: 0.75 | G29: 1 | H29: 0 | I29: 0 | J29: =E8 -> -2.5 | K29: 1 | L29: =F8 -> 0 | M29: 0 | N29: =C29*F29-D29*H29-J29*K29 -> 4.6675 | O29: =0.5*(C29*G29-D29*I29)-J29*(1-K29) -> 1.445 | P29: =N29+O29 -> 6.1125 | Q29: =L29*M29 -> 0 | R29: =L29-Q29 -> 0 | S29: 5 | T29: 3 | U29: =Assumptions!$C$7 -> 0.66666667 | V29: =1-Assumptions!$C$7 -> 0.33333333 | W29: 0 | X29: =U29+V29+W29 -> 1 | Y29: Agent layer off from April 2026 after Q1 contract review
A30: =A9 -> S1 · PdM: close the loop on current 150 machines | B30: =B9 -> W2 Maintenance | C30: =C9*IF(H9=1,Assumptions!$C$6,1) -> 1.875 | D30: =D9 -> 0.5 | E30: =C30-D30 -> 1.375 | F30: 0.5 | G30: 1 | H30: 0.75 | I30: 1 | J30: =E9 -> 0 | K30: 1 | L30: =F9 -> 0 | M30: 0 | N30: =C30*F30-D30*H30-J30*K30 -> 0.5625 | O30: =0.5*(C30*G30-D30*I30)-J30*(1-K30) -> 0.6875 | P30: =N30+O30 -> 1.25 | Q30: =L30*M30 -> 0 | R30: =L30-Q30 -> 0 | S30: 4 | T30: 4 | U30: =Assumptions!$C$7 -> 0.66666667 | V30: =1-Assumptions!$C$7 -> 0.33333333 | W30: 0 | X30: =U30+V30+W30 -> 1 | Y30: Work-order integration is the remaining 2026 scope; month-6 gate: ≥85% alerts closed on time
A31: =A10 -> S2 · PdM: scale to +150 assets (IEM-led, gated) | B31: =B10 -> W2 Maintenance | C31: =C10*IF(H10=1,Assumptions!$C$6,1) -> 2.625 | D31: =D10 -> 2.01 | E31: =C31-D31 -> 0.615 | F31: 0.2 | G31: 0.75 | H31: 0.4 | I31: 1 | J31: =E10 -> 2 | K31: 0.6 | L31: =F10 -> 8 | M31: 0.6 | N31: =C31*F31-D31*H31-J31*K31 -> -1.479 | O31: =0.5*(C31*G31-D31*I31)-J31*(1-K31) -> -0.820625 | P31: =N31+O31 -> -2.299625 | Q31: =L31*M31 -> 4.8 | R31: =L31-Q31 -> 3.2 | S31: 3 | T31: 9 | U31: =Assumptions!$C$39 -> 0.3 | V31: =1-Assumptions!$C$39 -> 0.7 | W31: 0 | X31: =U31+V31+W31 -> 1 | Y31: Capex released only after the S1 gate is met
A32: =A11 -> S3 · Vision: retrain & calibrate current 8 lines | B32: =B11 -> W3 Quality | C32: =C11*IF(H11=1,Assumptions!$C$6,1) -> 2.625 | D32: =D11 -> 0 | E32: =C32-D32 -> 2.625 | F32: 0.5 | G32: 1 | H32: 0 | I32: 0 | J32: =E11 -> 0.5 | K32: 1 | L32: =F11 -> 0 | M32: 0 | N32: =C32*F32-D32*H32-J32*K32 -> 0.8125 | O32: =0.5*(C32*G32-D32*I32)-J32*(1-K32) -> 1.3125 | P32: =N32+O32 -> 2.125 | Q32: =L32*M32 -> 0 | R32: =L32-Q32 -> 0 | S32: 4 | T32: 4 | U32: =Assumptions!$C$7 -> 0.66666667 | V32: 0 | W32: =1-Assumptions!$C$7 -> 0.33333333 | X32: =U32+V32+W32 -> 1 | Y32: Retraining in H1-26; month-6 gate: manual review ≤25% of flagged rejects
A33: =A12 -> S4 · Vision + traceability: +3 Auto lines (gated) | B33: =B12 -> W3 Quality | C33: =C12*IF(H12=1,Assumptions!$C$6,1) -> 0.984375 | D33: =D12 -> 1.005 | E33: =C33-D33 -> -0.020625 | F33: 0 | G33: 0.4 | H33: 0.1 | I33: 0.8 | J33: =E12 -> 0.8 | K33: 0.3 | L33: =F12 -> 4 | M33: 0.25 | N33: =C33*F33-D33*H33-J33*K33 -> -0.3405 | O33: =0.5*(C33*G33-D33*I33)-J33*(1-K33) -> -0.765125 | P33: =N33+O33 -> -1.105625 | Q33: =L33*M33 -> 1 | R33: =L33-Q33 -> 3 | S33: 3 | T33: 12 | U33: 1 | V33: 0 | W33: 0 | X33: =U33+V33+W33 -> 1 | Y33: Month-9 gate: S3 gate met AND named OEM programme requires traceability
A34: =A13 -> N1 · Energy management & optimisation | B34: =B13 -> W4 Energy & process | C34: =C13*IF(H13=1,Assumptions!$C$6,1) -> 4.8375 | D34: =D13 -> 0.8 | E34: =C34-D34 -> 4.0375 | F34: 0.4 | G34: 0.85 | H34: 0.6 | I34: 1 | J34: =E13 -> 1 | K34: 0.7 | L34: =F13 -> 3 | M34: 0.8 | N34: =C34*F34-D34*H34-J34*K34 -> 0.755 | O34: =0.5*(C34*G34-D34*I34)-J34*(1-K34) -> 1.3559375 | P34: =N34+O34 -> 2.1109375 | Q34: =L34*M34 -> 2.4 | R34: =L34-Q34 -> 0.6 | S34: 4 | T34: 6 | U34: =Case_Ops!$C$7*Assumptions!$C$49/C13 -> 0.41860465 | V34: =Case_Ops!$D$7*Assumptions!$C$50/C13 -> 0.11627907 | W34: =Case_Ops!$E$7*Assumptions!$C$51/C13 -> 0.46511628 | X34: =U34+V34+W34 -> 1 | Y34: Metering first, then scheduling and set-point optimisation — starts month 1
A35: =A14 -> N2 · SMC golden-batch & process control (gated) | B35: =B14 -> W4 Energy & process | C35: =C14*IF(H14=1,Assumptions!$C$6,1) -> 1.3953782 | D35: =D14 -> 0.4 | E35: =C35-D35 -> 0.99537815 | F35: 0.1 | G35: 0.6 | H35: 0.3 | I35: 1 | J35: =E14 -> 0.8 | K35: 0.5 | L35: =F14 -> 2 | M35: 0.5 | N35: =C35*F35-D35*H35-J35*K35 -> -0.38046218 | O35: =0.5*(C35*G35-D35*I35)-J35*(1-K35) -> -0.18138655 | P35: =N35+O35 -> -0.56184874 | Q35: =L35*M35 -> 1 | R35: =L35-Q35 -> 1 | S35: 2 | T35: 12 | U35: 0 | V35: 0 | W35: 1 | X35: =U35+V35+W35 -> 1 | Y35: Funded only if SMC passes the month-6 fix-or-exit gate
A36: =A15 -> N3 · Procurement spend analytics & should-cost | B36: =B15 -> W5 Procurement | C36: =C15*IF(H15=1,Assumptions!$C$6,1) -> 4.134375 | D36: =D15 -> 0.5 | E36: =C36-D36 -> 3.634375 | F36: 0.5 | G36: 0.9 | H36: 0.7 | I36: 1 | J36: =E15 -> 1 | K36: 0.8 | L36: =F15 -> 0 | M36: 0 | N36: =C36*F36-D36*H36-J36*K36 -> 0.9171875 | O36: =0.5*(C36*G36-D36*I36)-J36*(1-K36) -> 1.4104687 | P36: =N36+O36 -> 2.3276562 | Q36: =L36*M36 -> 0 | R36: =L36-Q36 -> 0 | S36: 4 | T36: 4 | U36: =Case_Financials!$F$54/Case_Financials!$F$6 -> 0.4789916 | V36: =Case_Financials!$F$55/Case_Financials!$F$6 -> 0.34033613 | W36: =Case_Financials!$F$56/Case_Financials!$F$6 -> 0.18067227 | X36: =U36+V36+W36 -> 1 | Y36: No-capex quick win: spend cube from AP data starts month 1
A37: =A16 -> N4 · Cost pass-through & quoting (index clauses, CPQ) | B37: =B16 -> W6 Commercial & back-office | C37: =C16*IF(H16=1,Assumptions!$C$6,1) -> 5.26875 | D37: =D16 -> 0.7 | E37: =C37-D37 -> 4.56875 | F37: 0.4 | G37: 0.85 | H37: 0.7 | I37: 1 | J37: =E16 -> 1 | K37: 0.8 | L37: =F16 -> 0 | M37: 0 | N37: =C37*F37-D37*H37-J37*K37 -> 0.8175 | O37: =0.5*(C37*G37-D37*I37)-J37*(1-K37) -> 1.6892187 | P37: =N37+O37 -> 2.5067188 | Q37: =L37*M37 -> 0 | R37: =L37-Q37 -> 0 | S37: 3 | T37: 6 | U37: =Case_Financials!$F$54*Assumptions!$C$63/C16 -> 0.40569395 | V37: =Case_Financials!$F$55*Assumptions!$C$64/C16 -> 0.28825623 | W37: =Case_Financials!$F$56*Assumptions!$C$65/C16 -> 0.30604982 | X37: =U37+V37+W37 -> 1 | Y37: Index clauses land at each OEM contract renewal; SMC/IEM quoting from month 2
A38: =A17 -> N6 · Back-office & customer-support automation | B38: =B17 -> W6 Commercial & back-office | C38: =C17*IF(H17=1,Assumptions!$C$6,1) -> 4.59 | D38: =D17 -> 1 | E38: =C38-D38 -> 3.59 | F38: 0.25 | G38: 0.7 | H38: 0.6 | I38: 1 | J38: =E17 -> 1 | K38: 0.7 | L38: =F17 -> 0 | M38: 0 | N38: =C38*F38-D38*H38-J38*K38 -> -0.1525 | O38: =0.5*(C38*G38-D38*I38)-J38*(1-K38) -> 0.8065 | P38: =N38+O38 -> 0.654 | Q38: =L38*M38 -> 0 | R38: =L38-Q38 -> 0 | S38: 4 | T38: 6 | U38: =Case_Financials!$F$54/Case_Financials!$F$6 -> 0.4789916 | V38: =Case_Financials!$F$55/Case_Financials!$F$6 -> 0.34033613 | W38: =Case_Financials!$F$56/Case_Financials!$F$6 -> 0.18067227 | X38: =U38+V38+W38 -> 1 | Y38: Customer-support copilot and consolidation automation; savings via attrition
A39: =A18 -> N5 · IEM connected-service pilot ("predictive service") | B39: =B18 -> W7 Service growth | C39: =C18*IF(H18=1,Assumptions!$C$6,1) -> 0.6075 | D39: =D18 -> 0 | E39: =C39-D39 -> 0.6075 | F39: 0.1 | G39: 0.5 | H39: 0 | I39: 0 | J39: =E18 -> 1 | K39: 0.6 | L39: =F18 -> 2 | M39: 0.6 | N39: =C39*F39-D39*H39-J39*K39 -> -0.53925 | O39: =0.5*(C39*G39-D39*I39)-J39*(1-K39) -> -0.248125 | P39: =N39+O39 -> -0.787375 | Q39: =L39*M39 -> 1.2 | R39: =L39-Q39 -> 0.8 | S39: 2 | T39: 12 | U39: 0 | V39: 1 | W39: 0 | X39: =U39+V39+W39 -> 1 | Y39: Pilot contracts signed H2-26; revenue in 2027
A40: =A19 -> O2 · Less: procurement savings passed to OEMs | B40: =B19 -> Overlap netting | C40: =C19*IF(H19=1,Assumptions!$C$6,1) -> -0.99016544 | D40: =D19 -> 0 | E40: =C40-D40 -> -0.99016544 | F40: 0.5 | G40: 0.9 | H40: 0 | I40: 0 | J40: =E19 -> 0 | K40: 0 | L40: =F19 -> 0 | M40: 0 | N40: =C40*F40-D40*H40-J40*K40 -> -0.49508272 | O40: =0.5*(C40*G40-D40*I40)-J40*(1-K40) -> -0.44557445 | P40: =N40+O40 -> -0.94065717 | Q40: =L40*M40 -> 0 | R40: =L40-Q40 -> 0 | U40: 1 | V40: 0 | W40: 0 | X40: =U40+V40+W40 -> 1 | Y40: Follows N3 phasing
A41: =A20 -> O3 · Less: OEM productivity give-backs | B41: =B20 -> Overlap netting | C41: =C20*IF(H20=1,Assumptions!$C$6,1) -> -1.6992188 | D41: =D20 -> 0 | E41: =C41-D41 -> -1.6992188 | F41: 0.35 | G41: 0.8 | H41: 0 | I41: 0 | J41: =E20 -> 0 | K41: 0 | L41: =F20 -> 0 | M41: 0 | N41: =C41*F41-D41*H41-J41*K41 -> -0.59472656 | O41: =0.5*(C41*G41-D41*I41)-J41*(1-K41) -> -0.6796875 | P41: =N41+O41 -> -1.2744141 | Q41: =L41*M41 -> 0 | R41: =L41-Q41 -> 0 | U41: 1 | V41: 0 | W41: 0 | X41: =U41+V41+W41 -> 1 | Y41: Follows PdM/vision/energy phasing
A42: Total | C42: =SUM(C27:C41) -> 29.143494 | D42: =SUM(D27:D41) -> 8.415 | E42: =SUM(E27:E41) -> 20.728494 | J42: =SUM(J27:J41) -> 10.1 | L42: =SUM(L27:L41) -> 29 | N42: =SUM(N27:N41) -> 1.300666 | O42: =SUM(O27:O41) -> 3.4666015 | P42: =SUM(P27:P41) -> 4.7672675 | Q42: =SUM(Q27:Q41) -> 16.4 | R42: =SUM(R27:R41) -> 12.6
A44: Part C — Workstream view (what the deck shows)
A45: Workstream | C45: Net RR | D45: EBITDA 2026 | E45: EBITDA H1-27 | F45: EBITDA 18m | G45: One-off 18m | H45: Capex 18m
A46: W1 Foundations | C46: =SUMIF($B$27:$B$41,$A46,$E$27:$E$41) -> 1.39 | D46: =SUMIF($B$27:$B$41,$A46,$N$27:$N$41) -> 1.4175 | E46: =SUMIF($B$27:$B$41,$A46,$O$27:$O$41) -> -0.655 | F46: =SUMIF($B$27:$B$41,$A46,$P$27:$P$41) -> 0.7625 | G46: =SUMIF($B$27:$B$41,$A46,$J$27:$J$41) -> 1 | H46: =SUMIF($B$27:$B$41,$A46,$L$27:$L$41) -> 10
A47: W2 Maintenance | C47: =SUMIF($B$27:$B$41,$A47,$E$27:$E$41) -> 1.99 | D47: =SUMIF($B$27:$B$41,$A47,$N$27:$N$41) -> -0.9165 | E47: =SUMIF($B$27:$B$41,$A47,$O$27:$O$41) -> -0.133125 | F47: =SUMIF($B$27:$B$41,$A47,$P$27:$P$41) -> -1.049625 | G47: =SUMIF($B$27:$B$41,$A47,$J$27:$J$41) -> 2 | H47: =SUMIF($B$27:$B$41,$A47,$L$27:$L$41) -> 8
A48: W3 Quality | C48: =SUMIF($B$27:$B$41,$A48,$E$27:$E$41) -> 2.604375 | D48: =SUMIF($B$27:$B$41,$A48,$N$27:$N$41) -> 0.472 | E48: =SUMIF($B$27:$B$41,$A48,$O$27:$O$41) -> 0.547375 | F48: =SUMIF($B$27:$B$41,$A48,$P$27:$P$41) -> 1.019375 | G48: =SUMIF($B$27:$B$41,$A48,$J$27:$J$41) -> 1.3 | H48: =SUMIF($B$27:$B$41,$A48,$L$27:$L$41) -> 4
A49: W4 Energy & process | C49: =SUMIF($B$27:$B$41,$A49,$E$27:$E$41) -> 5.0328782 | D49: =SUMIF($B$27:$B$41,$A49,$N$27:$N$41) -> 0.37453782 | E49: =SUMIF($B$27:$B$41,$A49,$O$27:$O$41) -> 1.1745509 | F49: =SUMIF($B$27:$B$41,$A49,$P$27:$P$41) -> 1.5490888 | G49: =SUMIF($B$27:$B$41,$A49,$J$27:$J$41) -> 1.8 | H49: =SUMIF($B$27:$B$41,$A49,$L$27:$L$41) -> 5
A50: W5 Procurement | C50: =SUMIF($B$27:$B$41,$A50,$E$27:$E$41) -> 3.634375 | D50: =SUMIF($B$27:$B$41,$A50,$N$27:$N$41) -> 0.9171875 | E50: =SUMIF($B$27:$B$41,$A50,$O$27:$O$41) -> 1.4104687 | F50: =SUMIF($B$27:$B$41,$A50,$P$27:$P$41) -> 2.3276562 | G50: =SUMIF($B$27:$B$41,$A50,$J$27:$J$41) -> 1 | H50: =SUMIF($B$27:$B$41,$A50,$L$27:$L$41) -> 0
A51: W6 Commercial & back-office | C51: =SUMIF($B$27:$B$41,$A51,$E$27:$E$41) -> 8.15875 | D51: =SUMIF($B$27:$B$41,$A51,$N$27:$N$41) -> 0.665 | E51: =SUMIF($B$27:$B$41,$A51,$O$27:$O$41) -> 2.4957187 | F51: =SUMIF($B$27:$B$41,$A51,$P$27:$P$41) -> 3.1607188 | G51: =SUMIF($B$27:$B$41,$A51,$J$27:$J$41) -> 2 | H51: =SUMIF($B$27:$B$41,$A51,$L$27:$L$41) -> 0
A52: W7 Service growth | C52: =SUMIF($B$27:$B$41,$A52,$E$27:$E$41) -> 0.6075 | D52: =SUMIF($B$27:$B$41,$A52,$N$27:$N$41) -> -0.53925 | E52: =SUMIF($B$27:$B$41,$A52,$O$27:$O$41) -> -0.248125 | F52: =SUMIF($B$27:$B$41,$A52,$P$27:$P$41) -> -0.787375 | G52: =SUMIF($B$27:$B$41,$A52,$J$27:$J$41) -> 1 | H52: =SUMIF($B$27:$B$41,$A52,$L$27:$L$41) -> 2
A53: Overlap netting | C53: =SUMIF($B$27:$B$41,$A53,$E$27:$E$41) -> -2.6893842 | D53: =SUMIF($B$27:$B$41,$A53,$N$27:$N$41) -> -1.0898093 | E53: =SUMIF($B$27:$B$41,$A53,$O$27:$O$41) -> -1.1252619 | F53: =SUMIF($B$27:$B$41,$A53,$P$27:$P$41) -> -2.2150712 | G53: =SUMIF($B$27:$B$41,$A53,$J$27:$J$41) -> 0 | H53: =SUMIF($B$27:$B$41,$A53,$L$27:$L$41) -> 0
A54: Total | C54: =SUM(C46:C53) -> 20.728494 | D54: =SUM(D46:D53) -> 1.300666 | E54: =SUM(E46:E53) -> 3.4666015 | F54: =SUM(F46:F53) -> 4.7672675 | G54: =SUM(G46:G53) -> 10.1 | H54: =SUM(H46:H53) -> 29
A55: Check: workstream total − initiative total (should be 0) | C55: =C54-E42 -> 0
A57: Part D — Working-capital release (cash only; separate from recurring EBITDA as the case requires)
A58: USD m | C58: 2025A | D58: Dec-26 | E58: Jun-27
A59: Inventory days | C59: =Diagnosis!$F$21 -> 100.08065 | D59: =Assumptions!$C$80 -> 96 | E59: =Assumptions!$C$81 -> 90
A60: Inventory balance (at 2025 COGS) | C60: =Case_Financials!$F$32 -> 255 | D60: =D59*Case_Financials!$F$7/365 -> 244.60274 | E60: =E59*Case_Financials!$F$7/365 -> 229.31507
A61: Inventory release in period | D61: =C60-D60 -> 10.39726 | E61: =D60-E60 -> 15.287671
A62: Receivable days | C62: =Diagnosis!$F$22 -> 52.756303 | D62: =Assumptions!$C$82 -> 51 | E62: =Assumptions!$C$83 -> 49
A63: Receivables balance (at 2025 revenue) | C63: =Case_Financials!$F$31 -> 172 | D63: =D62*Case_Financials!$F$6/365 -> 166.27397 | E63: =E62*Case_Financials!$F$6/365 -> 159.75342
A64: Receivables release in period | D64: =C63-D63 -> 5.7260274 | E64: =D63-E63 -> 6.5205479
A65: Total working-capital release | D65: =D61+D64 -> 16.123288 | E65: =E61+E64 -> 21.808219 | Y65: One-off cash, not EBITDA

Sheet Projection
A1: Projection — base (momentum) vs plan, Jan-2026 to Jun-2027
A2: Base = current digital scope continues and all capex requests are approved; no new initiatives. Plan = this strategy at the base-case realisation factor. RR columns annualise the June-2027 exit position.
A4: USD m | C4: 2025A | D4: 2026 Base | E4: H1-27 Base | F4: 18m Base | G4: 2026 Plan | H4: H1-27 Plan | I4: 18m Plan | J4: Jun-27 RR Base | K4: Jun-27 RR Plan | L4: Note
A5: EBITDA
A6: EBITDA 2025 (starting point) | C6: =Case_Financials!$F$10 -> 25 | D6: =C6 -> 25 | E6: =C6*0.5 -> 12.5 | F6: =D6+E6 -> 37.5 | G6: =C6 -> 25 | H6: =C6*0.5 -> 12.5 | I6: =G6+H6 -> 37.5 | J6: =C6 -> 25 | K6: =C6 -> 25 | L6: Revenue and underlying margin held at 2025 (Assumptions)
A7: One-off 2025 implementation costs rolling off (Ex.6) | D7: =Diagnosis!$C$66 -> 17 | E7: =Diagnosis!$C$64*0.5 -> 11.5 | F7: =D7+E7 -> 28.5 | G7: =D7 -> 17 | H7: =E7 -> 11.5 | I7: =G7+H7 -> 28.5 | J7: =Diagnosis!$C$64 -> 23 | K7: =Diagnosis!$C$64 -> 23 | L7: 23 of 2025 temporary costs do not recur; 6 of remaining work falls in 2026. Happens in both cases — not claimed
A8: Initiatives, net of costs (at realisation factor) | D8: 0 | E8: 0 | F8: =D8+E8 -> 0 | G8: =Initiatives!$N$42 -> 1.300666 | H8: =Initiatives!$O$42 -> 3.4666015 | I8: =G8+H8 -> 4.7672675 | J8: 0 | K8: =Initiatives!$E$42 -> 20.728494 | L8: Initiatives Part B
A9: EBITDA | C9: =SUM(C6:C8) -> 25 | D9: =SUM(D6:D8) -> 42 | E9: =SUM(E6:E8) -> 24 | F9: =SUM(F6:F8) -> 66 | G9: =SUM(G6:G8) -> 43.300666 | H9: =SUM(H6:H8) -> 27.466601 | I9: =SUM(I6:I8) -> 70.767268 | J9: =SUM(J6:J8) -> 48 | K9: =SUM(K6:K8) -> 68.728494
A10: Revenue (run-rate) | C10: =Case_Financials!$F$6 -> 1190 | J10: =Case_Financials!$F$6 -> 1190 | K10: =Case_Financials!$F$6+Initiatives!$G$21*Assumptions!$C$6 -> 1198.3063 | L10: Plan adds price realisation (N4) and service revenue (N5)
A11: EBITDA margin (run-rate) | C11: =C9/C10 -> 0.021008403 | J11: =J9/J10 -> 0.040336134 | K11: =K9/K10 -> 0.057354699
A12: Cash flow
A13: Interest at 2025 rate on opening debt | C13: =-Case_Financials!$F$13 -> -40 | D13: =-Assumptions!$C$9*(Case_Financials!$F$41+Case_Financials!$F$44) -> -42.289562 | E13: =-Assumptions!$C$9*D27*0.5 -> -23.64955 | F13: =D13+E13 -> -65.939113 | G13: =-Assumptions!$C$9*(Case_Financials!$F$41+Case_Financials!$F$44) -> -42.289562 | H13: =-Assumptions!$C$9*G27*0.5 -> -22.679208 | I13: =G13+H13 -> -64.968771 | J13: =-Assumptions!$C$9*E27 -> -49.925062 | K13: =-Assumptions!$C$9*H27 -> -46.277413 | L13: Implied 2025 rate × opening debt of each period
A14: Refinancing premium (short-term debt rolled + new money) | C14: 0 | D14: =-Assumptions!$C$10*Case_Financials!$F$41*0.5 -> -2.7 | E14: =-Assumptions!$C$10*(Case_Financials!$F$41+D25)*0.5 -> -4.0948434 | F14: =D14+E14 -> -6.7948434 | G14: =-Assumptions!$C$10*Case_Financials!$F$41*0.5 -> -2.7 | H14: =-Assumptions!$C$10*(Case_Financials!$F$41+G25)*0.5 -> -3.5544841 | I14: =G14+H14 -> -6.2544841 | J14: =-Assumptions!$C$10*(Case_Financials!$F$41+F25) -> -9.6520187 | K14: =-Assumptions!$C$10*(Case_Financials!$F$41+I25) -> -7.6207344 | L14: 180 matures through 2026 (rolled evenly → half-year of premium in 2026), fully repriced from 2027; new money priced the same
A15: Net finance costs | C15: =C13+C14 -> -40 | D15: =D13+D14 -> -44.989562 | E15: =E13+E14 -> -27.744394 | F15: =F13+F14 -> -72.733956 | G15: =G13+G14 -> -44.989562 | H15: =H13+H14 -> -26.233692 | I15: =I13+I14 -> -71.223255 | J15: =J13+J14 -> -59.57708 | K15: =K13+K14 -> -53.898147
A16: Cash tax | C16: =-Case_Financials!$F$15 -> 0 | D16: =-Assumptions!$C$12 -> 0 | E16: =-Assumptions!$C$12*0.5 -> 0 | F16: =D16+E16 -> 0 | G16: =-Assumptions!$C$12 -> 0 | H16: =-Assumptions!$C$12*0.5 -> 0 | I16: =G16+H16 -> 0 | L16: Losses: PBT check below
A17: Working-capital release (+) / build (−) | C17: =Case_Financials!$F$67 -> -11 | D17: 0 | E17: 0 | F17: =D17+E17 -> 0 | G17: =Initiatives!$D$65 -> 16.123288 | H17: =Initiatives!$E$65 -> 21.808219 | I17: =G17+H17 -> 37.931507 | L17: Base: days held flat. Plan: Initiatives Part D
A18: Operating cash flow after interest and tax | C18: =C9+C15+C16+C17 -> -26 | D18: =D9+D15+D16+D17 -> -2.9895623 | E18: =E9+E15+E16+E17 -> -3.7443939 | F18: =F9+F15+F16+F17 -> -6.7339562 | G18: =G9+G15+G16+G17 -> 14.434391 | H18: =H9+H15+H16+H17 -> 23.041128 | I18: =I9+I15+I16+I17 -> 37.47552
A19: Maintenance capex | C19: =Case_Financials!$F$69 -> -45 | D19: =-Assumptions!$C$21 -> -45 | E19: =-Assumptions!$C$21*0.5 -> -22.5 | F19: =D19+E19 -> -67.5 | G19: =-Assumptions!$C$21 -> -45 | H19: =-Assumptions!$C$21*0.5 -> -22.5 | I19: =G19+H19 -> -67.5 | L19: Held at 45/yr in both cases
A20: Upgrade & expansion capex | C20: =Case_Financials!$F$70 -> -25 | D20: =-Assumptions!$C$17 -> -25 | E20: =-Assumptions!$C$17*0.5 -> -12.5 | F20: =D20+E20 -> -37.5 | G20: =-Assumptions!$C$22 -> -10 | H20: =-Assumptions!$C$22*0.5 -> -5 | I20: =G20+H20 -> -15 | L20: Plan defers expansion: no segment is capacity-constrained
A21: Digital capex | C21: =Case_Financials!$F$71 -> -45 | D21: =-Assumptions!$C$18*Assumptions!$C$19 -> -20 | E21: =-Assumptions!$C$18*(1-Assumptions!$C$19) -> -10 | F21: =D21+E21 -> -30 | G21: =-Initiatives!$Q$42 -> -16.4 | H21: =-Initiatives!$R$42 -> -12.6 | I21: =G21+H21 -> -29 | L21: Base: 30 requested. Plan: re-prioritised, stage-gated portfolio
A22: Total capex | C22: =SUM(C19:C21) -> -115 | D22: =SUM(D19:D21) -> -90 | E22: =SUM(E19:E21) -> -45 | F22: =SUM(F19:F21) -> -135 | G22: =SUM(G19:G21) -> -71.4 | H22: =SUM(H19:H21) -> -40.1 | I22: =SUM(I19:I21) -> -111.5
A23: Free cash flow (before disposals and financing) | C23: =C18+C22 -> -141 | D23: =D18+D22 -> -92.989562 | E23: =E18+E22 -> -48.744394 | F23: =F18+F22 -> -141.73396 | G23: =G18+G22 -> -56.965609 | H23: =H18+H22 -> -17.058872 | I23: =I18+I22 -> -74.02448
A24: Balance sheet (all shortfalls funded with debt; funding bridge shown below)
A25: Debt raised (+) / repaid (−) to hold minimum cash | D25: =-D23-(Case_Financials!$F$30-Assumptions!$C$11) -> 92.989562 | E25: =-E23 -> 48.744394 | F25: =D25+E25 -> 141.73396 | G25: =-G23-(Case_Financials!$F$30-Assumptions!$C$11) -> 56.965609 | H25: =-H23 -> 17.058872 | I25: =G25+H25 -> 74.02448
A26: Closing cash | C26: =Case_Financials!$F$30 -> 30 | D26: =Assumptions!$C$11 -> 30 | E26: =Assumptions!$C$11 -> 30 | F26: =E26 -> 30 | G26: =Assumptions!$C$11 -> 30 | H26: =Assumptions!$C$11 -> 30 | I26: =H26 -> 30
A27: Closing debt | C27: =(Case_Financials!$F$41+Case_Financials!$F$44) -> 785 | D27: =C27+D25 -> 877.98956 | E27: =D27+E25 -> 926.73396 | F27: =E27 -> 926.73396 | G27: =C27+G25 -> 841.96561 | H27: =G27+H25 -> 859.02448 | I27: =H27 -> 859.02448
A28: Net debt | C28: =C27-C26 -> 755 | D28: =D27-D26 -> 847.98956 | E28: =E27-E26 -> 896.73396 | F28: =F27-F26 -> 896.73396 | G28: =G27-G26 -> 811.96561 | H28: =H27-H26 -> 829.02448 | I28: =I27-I26 -> 829.02448 | J28: =E28 -> 896.73396 | K28: =H28 -> 829.02448
A29: Credit metrics (period / run-rate)
A30: Net debt / EBITDA (run-rate at period end) | C30: =C28/C9 -> 30.2 | D30: =D28/D9 -> 20.190228 | E30: =E28/J9 -> 18.681957 | F30: =E30 -> 18.681957 | G30: =G28/G9 -> 18.751804 | H30: =H28/K9 -> 12.062311 | I30: =H30 -> 12.062311 | J30: =J28/J9 -> 18.681957 | K30: =K28/K9 -> 12.062311
A31: Interest cover (EBITDA / finance costs) | C31: =C9/-C15 -> 0.625 | D31: =D9/-D15 -> 0.93354987 | E31: =E9/-E15 -> 0.86503962 | F31: =F9/-F15 -> 0.90741661 | G31: =G9/-G15 -> 0.96246026 | H31: =H9/-H15 -> 1.0469972 | I31: =I9/-I15 -> 0.99359778 | J31: =J9/-J15 -> 0.80567896 | K31: =K9/-K15 -> 1.275155
A32: Check: PBT ≈ EBITDA − D&A − interest (must be < 0 for zero tax) | D32: =D9-Assumptions!$C$13+D15 -> -92.989562 | E32: =E9-Assumptions!$C$13*0.5+E15 -> -48.744394 | G32: =G9-Assumptions!$C$13+G15 -> -91.688896 | H32: =H9-Assumptions!$C$13*0.5+H15 -> -43.767091 | J32: =J9-Assumptions!$C$13+J15 -> -101.57708 | K32: =K9-Assumptions!$C$13+K15 -> -75.169654
A34: Lender view at Jun-27 — last twelve months (LTM) vs run-rate
C35: Base | D35: Plan | E35: Δ | L35: Note
A36: LTM EBITDA (≈ half of 2026 + H1-27) | C36: =0.5*D9+E9 -> 45 | D36: =0.5*G9+H9 -> 49.116935 | E36: =D36-C36 -> 4.1169345 | L36: Conservative for the plan: in a ramp, H2-26 > H1-26
A37: LTM net finance costs | C37: =-(0.5*D15+E15) -> 50.239175 | D37: =-(0.5*G15+H15) -> 48.728474 | E37: =D37-C37 -> -1.5107015
A38: LTM interest cover | C38: =C36/C37 -> 0.89571534 | D38: =D36/D37 -> 1.0079719 | E38: =D38-C38 -> 0.11225661 | L38: What lenders test at the refinancing
A39: Net debt at Jun-27 | C39: =E28 -> 896.73396 | D39: =H28 -> 829.02448 | E39: =D39-C39 -> -67.709476
A40: Net debt / LTM EBITDA | C40: =C39/C36 -> 19.927421 | D40: =D39/D36 -> 16.878588 | E40: =D40-C40 -> -3.0488337
A41: Run-rate EBITDA at Jun-27 | C41: =J9 -> 48 | D41: =K9 -> 68.728494 | E41: =D41-C41 -> 20.728494
A42: Run-rate interest cover | C42: =J31 -> 0.80567896 | D42: =K31 -> 1.275155 | E42: =D42-C42 -> 0.46947607
A43: Net debt / run-rate EBITDA | C43: =J30 -> 18.681957 | D43: =K30 -> 12.062311 | E43: =D43-C43 -> -6.6196463
A44: EBITDA needed for free-cash-flow break-even at run-rate | C44: =-J15+Assumptions!$C$21+Assumptions!$C$17+Assumptions!$C$14 -> 139.57708 | D44: =-K15+Assumptions!$C$21+Assumptions!$C$22+Assumptions!$C$14 -> 118.89815 | E44: =D44-C44 -> -20.678933 | L44: Interest + maintenance + expansion + steady-state digital capex
A45: Run-rate EBITDA minus break-even EBITDA | C45: =C41-C44 -> -91.57708 | D45: =D41-D44 -> -50.169654 | E45: =D45-C45 -> 41.407427 | L45: Negative = debt still grows after Jun-27 → balance-sheet action is required, digital alone cannot stop it
A47: Sources & uses of cash, Jan-26 to Jun-27 (funding bridge)
A48: USD m | C48: Base | D48: Plan | E48: Δ | L48: Note
A49: Use: free-cash-flow deficit | C49: =-F23 -> 141.73396 | D49: =-I23 -> 74.02448 | E49: =D49-C49 -> -67.709476
A50: Use: short-term debt falling due | C50: =Case_Financials!$F$41 -> 180 | D50: =Case_Financials!$F$41 -> 180 | E50: =D50-C50 -> 0
A51: Total uses | C51: =C49+C50 -> 321.73396 | D51: =D49+D50 -> 254.02448 | E51: =D51-C51 -> -67.709476
A52: Source: roll over short-term debt (at premium) | C52: =Case_Financials!$F$41 -> 180 | D52: =Case_Financials!$F$41 -> 180 | E52: =D52-C52 -> 0 | L52: Requires lenders to believe the plan: LTM cover above 1.0x
A53: Source: further non-core licence disposals | C53: =Assumptions!$C$85 -> 20 | D53: =Assumptions!$C$85 -> 20 | E53: =D53-C53 -> 0
A54: Source: sale-and-leaseback | C54: =Assumptions!$C$86 -> 40 | D54: =Assumptions!$C$86 -> 40 | E54: =D54-C54 -> 0
A55: Source: supply-chain finance / factoring | C55: =Assumptions!$C$87 -> 25 | D55: =Assumptions!$C$87 -> 25 | E55: =D55-C55 -> 0
A56: Source: new term debt / revolving credit (balancing) | C56: =C51-SUM(C52:C55) -> 56.733956 | D56: =D51-SUM(D52:D55) -> -10.97552 | E56: =D56-C56 -> -67.709476 | L56: Genuinely new money the CEO must raise
A57: Total sources | C57: =SUM(C52:C56) -> 321.73396 | D57: =SUM(D52:D56) -> 254.02448 | E57: =D57-C57 -> -67.709476
A59: Headlines (plan vs base)
C60: Value
A61: Run-rate EBITDA uplift at Jun-27 vs base | C61: =K9-J9 -> 20.728494
A62: 18-month free cash flow improvement vs base | C62: =I23-F23 -> 67.709476
A63: Net debt at Jun-27: plan minus base | C63: =H28-E28 -> -67.709476
A64: Net-debt build over 18 months: plan as % of base | C64: =(H28-C28)/(E28-C28) -> 0.52227767
A65: Digital & analytics benefits, Jun-27 RR (2025 realised + new, excl. F3) | C65: =Case_Digital!$F$9+(Initiatives!$C$42-Initiatives!$C$29) -> 39.253494
A66: Digital & AI opex, Jun-27 RR (recurring + central + new − F3 saving) | C66: =Case_Digital!$F$18+Case_Digital!$C$27+Initiatives!$D$42-Initiatives!$C$29 -> 30.525
A67: Net digital contribution, Jun-27 RR (2025: −35) | C67: =C65-C66 -> 8.728494

Sheet Segments
A1: Segments — June-2027 run-rate by business (USD m)
A2: Answers "where is a Group-wide approach right and where not?" and whether Auto moves out of forced-sale territory.
C4: Auto | D4: IEM | E4: SMC | F4: Group | H4: Note
A5: Revenue 2025 | C5: =Case_Financials!$F$54 -> 570 | D5: =Case_Financials!$F$55 -> 405 | E5: =Case_Financials!$F$56 -> 215 | F5: =SUM(C5:E5) -> 1190
A6: EBITDA 2025 | C6: =Case_Financials!$F$58 -> 5 | D6: =Case_Financials!$F$59 -> 33 | E6: =Case_Financials!$F$60 -> -13 | F6: =SUM(C6:E6) -> 25
A7: EBITDA margin 2025 | C7: =C6/C5 -> 0.0087719298 | D7: =D6/D5 -> 0.081481481 | E7: =E6/E5 -> -0.060465116 | F7: =F6/F5 -> 0.021008403
A8: One-off implementation costs rolling off | C8: =Case_Digital!$F$22*Assumptions!$C$7 -> 15.333333 | D8: =(Case_Digital!$C$22+Case_Digital!$E$22)*(1-Assumptions!$C$7) -> 5 | E8: =Case_Digital!$D$22*(1-Assumptions!$C$7) -> 2.6666667 | F8: =SUM(C8:E8) -> 23 | H8: PdM & SCP third plant is IEM; Vision third plant is SMC (Ex.7)
A9: Initiatives, net run-rate (incl. overlap netting) | C9: =SUMPRODUCT(Initiatives!$E$27:$E$41,Initiatives!$U$27:$U$41) -> 8.3533822 | D9: =SUMPRODUCT(Initiatives!$E$27:$E$41,Initiatives!$V$27:$V$41) -> 6.1943257 | E9: =SUMPRODUCT(Initiatives!$E$27:$E$41,Initiatives!$W$27:$W$41) -> 6.1807861 | F9: =SUM(C9:E9) -> 20.728494 | H9: Net run-rate × segment split (Initiatives Part B)
A10: EBITDA — Jun-27 run-rate | C10: =C6+C8+C9 -> 28.686716 | D10: =D6+D8+D9 -> 44.194326 | E10: =E6+E8+E9 -> -4.1525473 | F10: =SUM(C10:E10) -> 68.728494
A11: Check: Group vs Projection run-rate (should be 0) | F11: =F10-Projection!$K$9 -> 0
A12: Revenue — Jun-27 run-rate | C12: =Case_Financials!$F$54*(1+Assumptions!$C$63*Assumptions!$C$6) -> 572.1375 | D12: =Case_Financials!$F$55*(1+(Assumptions!$C$64+Assumptions!$C$68)*Assumptions!$C$6) -> 409.55625 | E12: =Case_Financials!$F$56*(1+Assumptions!$C$65*Assumptions!$C$6) -> 216.6125 | F12: =SUM(C12:E12) -> 1198.3063
A13: EBITDA margin — Jun-27 run-rate | C13: =C10/C12 -> 0.050139548 | D13: =D10/D12 -> 0.10790783 | E13: =E10/E12 -> -0.019170395 | F13: =F10/F12 -> 0.057354699 | H13: Auto profitable again but below its own 11.1% (2022). Supplier benchmarks are mostly EBIT (after D&A): compare like-for-like
A14: Margin change (pp) | C14: =C13-C7 -> 0.041367618 | D14: =D13-D7 -> 0.026426347 | E14: =E13-E7 -> 0.041294721 | F14: =F13-F7 -> 0.036346295
A15: Capacity utilisation 2025 (context) | C15: =Case_Ops!$C$6 -> 0.72 | D15: =Case_Ops!$D$6 -> 0.81 | E15: =Case_Ops!$E$6 -> 0.67 | H15: Auto & SMC are demand-constrained: downtime reduction saves cost there, adds throughput only in IEM
A16: SMC price realisation needed for break-even (vs 1.0% assumed) | E16: =Assumptions!$C$65-E10/(Case_Financials!$F$56*Assumptions!$C$6) -> 0.035752231 | H16: The month-6 fix-or-exit test
A18: SMC exit case (run-rate EBITDA effect only)
A19: SMC run-rate EBITDA removed | F19: =-E10 -> 4.1525473
A20: Stranded central digital & foundation costs left with the Group | F20: =-(Case_Digital!$C$27+Assumptions!$C$26+Assumptions!$C$27)*Case_Financials!$F$56/Case_Financials!$F$6 -> -2.4390756 | H20: Excludes undisclosed corporate overhead allocated to SMC → understates the stranded cost
A21: Change in Group run-rate EBITDA from exiting SMC | F21: =F19+F20 -> 1.7134716 | H21: Close to zero: exit is not an EBITDA fix; its value is cash (working capital, capex) and management focus. Loss-making unit → minimal proceeds

Sheet Sensitivity
A1: Sensitivity — how robust is the Jun-27 position?
A3: 1. Benefit realisation (initiative benefits scaled, except contractual F3; costs unchanged)
C4: Downside | D4: Base | E4: Stretch | F4: Upside | H4: Note
A5: Benefit realisation | C5: 0.5 | D5: 0.75 | E5: 1 | F5: 1.25
A6: Jun-27 run-rate EBITDA | C6: =Projection!$J$9+Initiatives!$C$23+Initiatives!$C$22*C5-Initiatives!$D$21 -> 59.977329 | D6: =Projection!$J$9+Initiatives!$C$23+Initiatives!$C$22*D5-Initiatives!$D$21 -> 68.728494 | E6: =Projection!$J$9+Initiatives!$C$23+Initiatives!$C$22*E5-Initiatives!$D$21 -> 77.479659 | F6: =Projection!$J$9+Initiatives!$C$23+Initiatives!$C$22*F5-Initiatives!$D$21 -> 86.230823 | H6: Momentum run-rate + benefits × factor − recurring costs
A7: EBITDA margin | C7: =C6/Projection!$J$10 -> 0.050401117 | D7: =D6/Projection!$J$10 -> 0.057755037 | E7: =E6/Projection!$J$10 -> 0.065108957 | F7: =F6/Projection!$J$10 -> 0.072462877
A8: Net debt / run-rate EBITDA (net debt at base-case plan) | C8: =Projection!$K$28/C6 -> 13.822297 | D8: =Projection!$K$28/D6 -> 12.062311 | E8: =Projection!$K$28/E6 -> 10.699898 | F8: =Projection!$K$28/F6 -> 9.6140156 | H8: Approximation: holds Jun-27 net debt at the base-case plan value
A9: Run-rate interest cover | C9: =C6/-Projection!$K$15 -> 1.1127902 | D9: =D6/-Projection!$K$15 -> 1.275155 | E9: =E6/-Projection!$K$15 -> 1.4375199 | F9: =F6/-Projection!$K$15 -> 1.5998847
A10: Realisation needed for run-rate interest cover of 1.5x | C10: =(-1.5*Projection!$K$15-Projection!$J$9-Initiatives!$C$23+Initiatives!$D$21)/Initiatives!$C$22 -> 1.0962033
A11: Realisation needed for run-rate interest cover of 2.0x | C11: =(-2*Projection!$K$15-Projection!$J$9-Initiatives!$C$23+Initiatives!$D$21)/Initiatives!$C$22 -> 1.8660743 | H11: Above 100% → 2.0x needs balance-sheet action, not more digital
A13: 2. One-at-a-time shocks to Jun-27 run-rate EBITDA (base-case plan)
C14: Shock | D14: Δ EBITDA | E14: EBITDA after | F14: Cover after | H14: Note
A15: Auto OEM price-down not recovered | C15: 0.01 | D15: =-Case_Financials!$F$54*C15 -> -5.7 | E15: =Projection!$K$9+D15 -> 63.028494 | F15: =E15/-Projection!$K$15 -> 1.1694 | H15: Each 1% ≈ 5.7 — why index-linked pass-through (N4) matters
A16: Auto OEM volume loss | C16: 0.05 | D16: =-Case_Financials!$F$54*C16*Assumptions!$C$89 -> -7.125 | E16: =Projection!$K$9+D16 -> 61.603494 | F16: =E16/-Projection!$K$15 -> 1.1429612 | H16: At 25% contribution margin; utilisation would fall further below 72%
A17: Energy price increase | C17: 0.1 | D17: =-Case_Ops!$F$7*C17 -> -12 | E17: =Projection!$K$9+D17 -> 56.728494 | F17: =E17/-Projection!$K$15 -> 1.0525129 | H17: Energy is 120 of COGS; N1 metering and N4 index clauses partly hedge
A18: PdM & vision scale-ups stopped at their gates | C18: 1 | D18: =-(Initiatives!$E$31+Initiatives!$E$33)*C18 -> -0.594375 | E18: =Projection!$K$9+D18 -> 68.134119 | F18: =E18/-Projection!$K$15 -> 1.2641273 | H18: Small: gates cap the downside
A19: Procurement & pass-through deliver only this share | C19: 0.5 | D19: =-(Initiatives!$C$36+Initiatives!$C$37+Initiatives!$C$40)*(1-C19) -> -4.2064798 | E19: =Projection!$K$9+D19 -> 64.522014 | F19: =E19/-Projection!$K$15 -> 1.1971101 | H19: Net of the O2 overlap
A20: Exit SMC | C20: exit | D20: =Segments!$F$21 -> 1.7134716 | E20: =Projection!$K$9+D20 -> 70.441966 | F20: =E20/-Projection!$K$15 -> 1.306946 | H20: From Segments: near-neutral on EBITDA
A21: Refinancing premium +200bp higher than assumed | C21: 0.02 | F21: =Projection!$K$9/(-Projection!$K$15+C21*(Case_Financials!$F$41+Projection!$I$25)) -> 1.1653117 | H21: Interest, not EBITDA: applied to the 180 + new money

Sheet Sources
A1: Sources — external benchmarks (verified 30 Sep 2026)
A2: Case data is authoritative; benchmarks are used only to size assumptions where the case is silent.
A4: ID | B4: Benchmark (quoted from source) | C4: Source | D4: Used for | E4: URL | F4: Accessed
A5: B1 | B5: Predictive maintenance typically reduces machine downtime by 30–50% and increases machine life by 20–40% | C5: McKinsey & Company, "Manufacturing: Analytics unleashes productivity and profitability", 14 Aug 2017 | D5: S1, S2 downtime target | E5: https://www.mckinsey.com/capabilities/operations/our-insights/manufacturing-analytics-unleashes-productivity-and-profitability | F5: 30-Sep-26
A6: B2 | B6: Optimised advanced process controls: up to 15% more throughput, 5% more yield, 10% less energy | C6: McKinsey & Company, "The potential of advanced process controls in energy and materials", 23 Nov 2020 | D6: N1 energy, N2 yield | E6: https://www.mckinsey.com/industries/metals-and-mining/our-insights/the-potential-of-advanced-process-controls-in-energy-and-materials | F6: 30-Sep-26
A7: B3 | B7: ISO 50001-certified facilities achieve ~4.1% annual energy-performance improvement in the first year and ~3.4% after twelve years | C7: Fitzgerald, Therkelsen, Sheaffer, Rao (Lawrence Berkeley National Laboratory), "Deeper and persistent energy savings and CO2 reductions achieved through ISO 50001 in the manufacturing sector", 2023 | D7: N1 energy | E7: https://smartersmallbuildings.lbl.gov/publications/deeper-and-persistent-energy-savings | F7: 30-Sep-26
A8: B4 | B8: Reducing overall spending by 6–12% is a realistic goal in chemicals procurement | C8: McKinsey & Company, "Technology-enabled procurement for chemical companies", 1 Oct 2019 | D8: N3 procurement | E8: https://www.mckinsey.com/industries/chemicals/our-insights/technology-enabled-procurement-for-chemical-companies | F8: 30-Sep-26
A9: B5 | B9: Across 1,000+ pricing-excellence initiatives, return on sales typically rises 2–7 percentage points | C9: McKinsey & Company, "Turning pricing power into profit", 1 Mar 2015 | D9: N4 commercial | E9: https://www.mckinsey.com/capabilities/growth-marketing-and-sales/our-insights/turning-pricing-power-into-profit | F9: 30-Sep-26
A10: B6 | B10: Average EBIT margin for aftermarket services 25% vs 10% for new equipment (30 industries) | C10: McKinsey & Company, "Industrial aftermarket services: Growing the core", 27 Jul 2017 | D10: N5 service margin | E10: https://www.mckinsey.com/industries/industrials/our-insights/industrial-aftermarket-services-growing-the-core | F10: 30-Sep-26
A11: B7 | B11: Diagnosed ~20% inventory-reduction opportunity; achieved 30% reduction with OTIF rising to 95% | C11: McKinsey & Company, "Supply Chain 4.0: Opportunities to use your supply chain for differentiation", 24 May 2019 | D11: Inventory days target | E11: https://www.mckinsey.com/capabilities/operations/our-insights/operations-blog/supply-chain-40-opportunities-to-use-your-supply-chain-for-differentiation | F11: 30-Sep-26
A12: B8 | B12: Generative AI applied to customer care could increase productivity by 30–45% of current function costs | C12: McKinsey & Company, "The economic potential of generative AI: The next productivity frontier", 14 Jun 2023 | D12: N6 back-office & support automation | E12: https://www.mckinsey.com/capabilities/mckinsey-digital/our-insights/the-economic-potential-of-generative-ai-the-next-productivity-frontier | F12: 30-Sep-26
